{
"meta":{"test_sets":[],"test_metrics":[],"learn_metrics":[{"best_value":"Min","name":"RMSE"}],"launch_mode":"Train","parameters":"","iteration_count":1000,"learn_sets":["learn"],"name":"experiment"},
"iterations":[
{"learn":[10.96237433],"iteration":0,"passed_time":0.5083457335,"remaining_time":507.8373877},
{"learn":[8.845189283],"iteration":1,"passed_time":1.078882619,"remaining_time":538.3624271},
{"learn":[7.418121068],"iteration":2,"passed_time":1.58011171,"remaining_time":525.1237917},
{"learn":[6.368510953],"iteration":3,"passed_time":2.067862184,"remaining_time":514.8976837},
{"learn":[5.628413008],"iteration":4,"passed_time":2.554749008,"remaining_time":508.3950527},
{"learn":[5.084100356],"iteration":5,"passed_time":3.034685673,"remaining_time":502.7462598},
{"learn":[4.544074496],"iteration":6,"passed_time":3.536074262,"remaining_time":501.6173918},
{"learn":[4.155207016],"iteration":7,"passed_time":3.985635395,"remaining_time":494.218789},
{"learn":[3.832259791],"iteration":8,"passed_time":4.495199682,"remaining_time":494.9714316},
{"learn":[3.617425186],"iteration":9,"passed_time":4.971244384,"remaining_time":492.153194},
{"learn":[3.409622441],"iteration":10,"passed_time":5.425149269,"remaining_time":487.7702388},
{"learn":[3.277934815],"iteration":11,"passed_time":5.915444083,"remaining_time":487.0382295},
{"learn":[3.168596875],"iteration":12,"passed_time":6.394386868,"remaining_time":485.481526},
{"learn":[3.023694],"iteration":13,"passed_time":6.8655743,"remaining_time":483.53259},
{"learn":[2.887811636],"iteration":14,"passed_time":7.321863866,"remaining_time":480.8023939},
{"learn":[2.806272167],"iteration":15,"passed_time":7.78128812,"remaining_time":478.5492194},
{"learn":[2.68593678],"iteration":16,"passed_time":8.208914421,"remaining_time":474.6684045},
{"learn":[2.636501238],"iteration":17,"passed_time":8.616978358,"remaining_time":470.1040415},
{"learn":[2.533728119],"iteration":18,"passed_time":9.035390405,"remaining_time":466.511473},
{"learn":[2.475644569],"iteration":19,"passed_time":9.513986059,"remaining_time":466.1853169},
{"learn":[2.400065806],"iteration":20,"passed_time":9.974559009,"remaining_time":465.0044414},
{"learn":[2.322607559],"iteration":21,"passed_time":10.43991547,"remaining_time":464.1016967},
{"learn":[2.288225729],"iteration":22,"passed_time":10.93222852,"remaining_time":464.3820549},
{"learn":[2.252707677],"iteration":23,"passed_time":11.39140988,"remaining_time":463.2506685},
{"learn":[2.198651151],"iteration":24,"passed_time":11.85129179,"remaining_time":462.2003798},
{"learn":[2.146481308],"iteration":25,"passed_time":12.27816956,"remaining_time":459.9591212},
{"learn":[2.109783265],"iteration":26,"passed_time":12.73343561,"remaining_time":458.8752906},
{"learn":[2.06829015],"iteration":27,"passed_time":13.21335542,"remaining_time":458.6921953},
{"learn":[2.042164556],"iteration":28,"passed_time":13.71303554,"remaining_time":459.1502589},
{"learn":[2.013740997],"iteration":29,"passed_time":14.1600752,"remaining_time":457.8424314},
{"learn":[1.979011699],"iteration":30,"passed_time":14.63346214,"remaining_time":457.4137036},
{"learn":[1.946209323],"iteration":31,"passed_time":15.07076948,"remaining_time":455.8907768},
{"learn":[1.922394876],"iteration":32,"passed_time":15.51830088,"remaining_time":454.733241},
{"learn":[1.898675488],"iteration":33,"passed_time":15.92913998,"remaining_time":452.5749771},
{"learn":[1.866596218],"iteration":34,"passed_time":16.36588813,"remaining_time":451.2309155},
{"learn":[1.855133435],"iteration":35,"passed_time":16.83228885,"remaining_time":450.7312903},
{"learn":[1.831204568],"iteration":36,"passed_time":17.26964572,"remaining_time":449.4775359},
{"learn":[1.807977207],"iteration":37,"passed_time":17.72933873,"remaining_time":448.8322068},
{"learn":[1.793539191],"iteration":38,"passed_time":18.2047456,"remaining_time":448.5836032},
{"learn":[1.765690519],"iteration":39,"passed_time":18.67872236,"remaining_time":448.2893367},
{"learn":[1.752417651],"iteration":40,"passed_time":19.20094201,"remaining_time":449.1147167},
{"learn":[1.741662498],"iteration":41,"passed_time":19.71571599,"remaining_time":449.7060933},
{"learn":[1.725344745],"iteration":42,"passed_time":20.14264855,"remaining_time":448.2910386},
{"learn":[1.70474783],"iteration":43,"passed_time":20.5483137,"remaining_time":446.4588158},
{"learn":[1.679862261],"iteration":44,"passed_time":20.96667704,"remaining_time":444.9594795},
{"learn":[1.669420128],"iteration":45,"passed_time":21.39881774,"remaining_time":443.7928722},
{"learn":[1.655101661],"iteration":46,"passed_time":21.85710757,"remaining_time":443.1877344},
{"learn":[1.647243015],"iteration":47,"passed_time":22.31557831,"remaining_time":442.5923031},
{"learn":[1.634087312],"iteration":48,"passed_time":22.79386399,"remaining_time":442.3870338},
{"learn":[1.622110527],"iteration":49,"passed_time":23.22679207,"remaining_time":441.3090493},
{"learn":[1.598647769],"iteration":50,"passed_time":23.69206235,"remaining_time":440.8581799},
{"learn":[1.591599239],"iteration":51,"passed_time":24.17875605,"remaining_time":440.7973219},
{"learn":[1.571549939],"iteration":52,"passed_time":24.58530006,"remaining_time":439.288286},
{"learn":[1.555748393],"iteration":53,"passed_time":25.03264807,"remaining_time":438.5349087},
{"learn":[1.533648241],"iteration":54,"passed_time":25.45596584,"remaining_time":437.3797767},
{"learn":[1.532244225],"iteration":55,"passed_time":25.91869311,"remaining_time":436.9151125},
{"learn":[1.517907045],"iteration":56,"passed_time":26.35732062,"remaining_time":436.0518131},
{"learn":[1.505466583],"iteration":57,"passed_time":26.79200469,"remaining_time":435.1391107},
{"learn":[1.488481114],"iteration":58,"passed_time":27.25665082,"remaining_time":434.7204818},
{"learn":[1.478038472],"iteration":59,"passed_time":27.70340613,"remaining_time":434.0200294},
{"learn":[1.46188273],"iteration":60,"passed_time":28.17083395,"remaining_time":433.646116},
{"learn":[1.452102248],"iteration":61,"passed_time":28.63460885,"remaining_time":433.2139209},
{"learn":[1.446578948],"iteration":62,"passed_time":29.1167165,"remaining_time":433.0533867},
{"learn":[1.435691368],"iteration":63,"passed_time":29.60265781,"remaining_time":432.9388704},
{"learn":[1.422764391],"iteration":64,"passed_time":30.05331664,"remaining_time":432.3054008},
{"learn":[1.409518676],"iteration":65,"passed_time":30.52899404,"remaining_time":432.0315218},
{"learn":[1.403578637],"iteration":66,"passed_time":30.94582536,"remaining_time":430.9321651},
{"learn":[1.396413675],"iteration":67,"passed_time":31.42241737,"remaining_time":430.6719557},
{"learn":[1.38678927],"iteration":68,"passed_time":31.86685284,"remaining_time":429.9715941},
{"learn":[1.383867731],"iteration":69,"passed_time":32.30416258,"remaining_time":429.1838742},
{"learn":[1.376046071],"iteration":70,"passed_time":32.79800465,"remaining_time":429.1457228},
{"learn":[1.363027744],"iteration":71,"passed_time":33.27805007,"remaining_time":428.9170898},
{"learn":[1.354182864],"iteration":72,"passed_time":33.75952241,"remaining_time":428.6996887},
{"learn":[1.347420658],"iteration":73,"passed_time":34.20673839,"remaining_time":428.0464831},
{"learn":[1.34367701],"iteration":74,"passed_time":34.67506514,"remaining_time":427.6591367},
{"learn":[1.33706123],"iteration":75,"passed_time":35.17941379,"remaining_time":427.7076098},
{"learn":[1.324795515],"iteration":76,"passed_time":35.63190348,"remaining_time":427.1200897},
{"learn":[1.320804966],"iteration":77,"passed_time":36.13808694,"remaining_time":427.17072},
{"learn":[1.311219898],"iteration":78,"passed_time":36.60094202,"remaining_time":426.7021215},
{"learn":[1.302354027],"iteration":79,"passed_time":37.040458,"remaining_time":425.965267},
{"learn":[1.294526281],"iteration":80,"passed_time":37.5011737,"remaining_time":425.4762794},
{"learn":[1.289336536],"iteration":81,"passed_time":37.9775213,"remaining_time":425.1629823},
{"learn":[1.281746923],"iteration":82,"passed_time":38.46426772,"remaining_time":424.9606446},
{"learn":[1.278421696],"iteration":83,"passed_time":38.95359954,"remaining_time":424.7797283},
{"learn":[1.272690517],"iteration":84,"passed_time":39.42892394,"remaining_time":424.4407695},
{"learn":[1.266976527],"iteration":85,"passed_time":39.86643494,"remaining_time":423.696762},
{"learn":[1.25587071],"iteration":86,"passed_time":40.30207822,"remaining_time":422.9402002},
{"learn":[1.251715658],"iteration":87,"passed_time":40.77623832,"remaining_time":422.5901062},
{"learn":[1.244683156],"iteration":88,"passed_time":41.23237794,"remaining_time":422.0527674},
{"learn":[1.243530765],"iteration":89,"passed_time":41.72195991,"remaining_time":421.8553724},
{"learn":[1.238073528],"iteration":90,"passed_time":42.13166061,"remaining_time":420.8536208},
{"learn":[1.236216475],"iteration":91,"passed_time":42.63684024,"remaining_time":420.8070754},
{"learn":[1.226378122],"iteration":92,"passed_time":43.06961675,"remaining_time":420.0445419},
{"learn":[1.221248813],"iteration":93,"passed_time":43.53635727,"remaining_time":419.6163796},
{"learn":[1.212300764],"iteration":94,"passed_time":44.01274306,"remaining_time":419.2792891},
{"learn":[1.206547119],"iteration":95,"passed_time":44.47941389,"remaining_time":418.8478142},
{"learn":[1.19581188],"iteration":96,"passed_time":44.91814442,"remaining_time":418.1555094},
{"learn":[1.190129752],"iteration":97,"passed_time":45.38239642,"remaining_time":417.7032813},
{"learn":[1.189100249],"iteration":98,"passed_time":45.77877138,"remaining_time":416.6330608},
{"learn":[1.185581799],"iteration":99,"passed_time":46.26753808,"remaining_time":416.4078427},
{"learn":[1.185026713],"iteration":100,"passed_time":46.48353581,"remaining_time":413.749492},
{"learn":[1.182290102],"iteration":101,"passed_time":46.94286417,"remaining_time":413.2812944},
{"learn":[1.177465244],"iteration":102,"passed_time":47.42813773,"remaining_time":413.0392189},
{"learn":[1.173025252],"iteration":103,"passed_time":47.9223786,"remaining_time":412.8697233},
{"learn":[1.168002977],"iteration":104,"passed_time":48.35882929,"remaining_time":412.2014497},
{"learn":[1.161805277],"iteration":105,"passed_time":48.84656416,"remaining_time":411.9700789},
{"learn":[1.157785506],"iteration":106,"passed_time":49.29285576,"remaining_time":411.3880392},
{"learn":[1.140678],"iteration":107,"passed_time":49.75853831,"remaining_time":410.9686683},
{"learn":[1.138999715],"iteration":108,"passed_time":50.23800424,"remaining_time":410.6611172},
{"learn":[1.138453463],"iteration":109,"passed_time":50.71780133,"remaining_time":410.3531199},
{"learn":[1.133037818],"iteration":110,"passed_time":51.15465396,"remaining_time":409.6980844},
{"learn":[1.127030818],"iteration":111,"passed_time":51.59399234,"remaining_time":409.0666535},
{"learn":[1.124012068],"iteration":112,"passed_time":52.05387384,"remaining_time":408.5998769},
{"learn":[1.119808187],"iteration":113,"passed_time":52.5131748,"remaining_time":408.1287094},
{"learn":[1.116934559],"iteration":114,"passed_time":52.95232664,"remaining_time":407.5026876},
{"learn":[1.113824421],"iteration":115,"passed_time":53.40621558,"remaining_time":406.9921946},
{"learn":[1.109026375],"iteration":116,"passed_time":53.86827573,"remaining_time":406.5443374},
{"learn":[1.105728229],"iteration":117,"passed_time":54.33526073,"remaining_time":406.1330505},
{"learn":[1.101759149],"iteration":118,"passed_time":54.76531794,"remaining_time":405.4474379},
{"learn":[1.098831527],"iteration":119,"passed_time":55.24014984,"remaining_time":405.0944321},
{"learn":[1.097958143],"iteration":120,"passed_time":55.71653696,"remaining_time":404.7507107},
{"learn":[1.0926046],"iteration":121,"passed_time":56.20544073,"remaining_time":404.4948931},
{"learn":[1.089299689],"iteration":122,"passed_time":56.63762828,"remaining_time":403.8308943},
{"learn":[1.083912999],"iteration":123,"passed_time":57.08244402,"remaining_time":403.2598465},
{"learn":[1.081996413],"iteration":124,"passed_time":57.56891985,"remaining_time":402.982439},
{"learn":[1.074356181],"iteration":125,"passed_time":58.00951605,"remaining_time":402.3834685},
{"learn":[1.071860465],"iteration":126,"passed_time":58.49697479,"remaining_time":402.1091259},
{"learn":[1.06790106],"iteration":127,"passed_time":58.98085356,"remaining_time":401.8070649},
{"learn":[1.063113488],"iteration":128,"passed_time":59.45395737,"remaining_time":401.4294331},
{"learn":[1.062900876],"iteration":129,"passed_time":59.7701888,"remaining_time":400.0004943},
{"learn":[1.053287361],"iteration":130,"passed_time":60.26664539,"remaining_time":399.7840828},
{"learn":[1.047036476],"iteration":131,"passed_time":60.70712629,"remaining_time":399.1953456},
{"learn":[1.044530389],"iteration":132,"passed_time":61.18148183,"remaining_time":398.8296597},
{"learn":[1.041861428],"iteration":133,"passed_time":61.68320887,"remaining_time":398.6392454},
{"learn":[1.040258578],"iteration":134,"passed_time":62.17467752,"remaining_time":398.3784893},
{"learn":[1.031429378],"iteration":135,"passed_time":62.66680495,"remaining_time":398.1185255},
{"learn":[1.0304556],"iteration":136,"passed_time":63.1837059,"remaining_time":398.0112277},
{"learn":[1.026950199],"iteration":137,"passed_time":63.65947915,"remaining_time":397.6410944},
{"learn":[1.023320556],"iteration":138,"passed_time":64.08659433,"remaining_time":396.9680412},
{"learn":[1.020659303],"iteration":139,"passed_time":64.59373423,"remaining_time":396.7900817},
{"learn":[1.019608928],"iteration":140,"passed_time":65.08061385,"remaining_time":396.4840234},
{"learn":[1.016751422],"iteration":141,"passed_time":65.53648374,"remaining_time":395.9880496},
{"learn":[1.013575011],"iteration":142,"passed_time":65.99972875,"remaining_time":395.5368359},
{"learn":[1.012240415],"iteration":143,"passed_time":66.49725765,"remaining_time":395.2892538},
{"learn":[1.010127214],"iteration":144,"passed_time":67.03429788,"remaining_time":395.2712048},
{"learn":[1.008859325],"iteration":145,"passed_time":67.59321195,"remaining_time":395.3739932},
{"learn":[1.008237203],"iteration":146,"passed_time":67.94336049,"remaining_time":394.2563707},
{"learn":[1.005877153],"iteration":147,"passed_time":68.39902762,"remaining_time":393.7565644},
{"learn":[1.004008936],"iteration":148,"passed_time":68.87360518,"remaining_time":393.3653558},
{"learn":[1.000819766],"iteration":149,"passed_time":69.40559678,"remaining_time":393.2983817},
{"learn":[0.9980771807],"iteration":150,"passed_time":69.8717032,"remaining_time":392.854808},
{"learn":[0.9947736896],"iteration":151,"passed_time":70.36809193,"remaining_time":392.5798813},
{"learn":[0.9926602903],"iteration":152,"passed_time":70.84664168,"remaining_time":392.203304},
{"learn":[0.9903413419],"iteration":153,"passed_time":71.31440592,"remaining_time":391.766152},
{"learn":[0.9874304949],"iteration":154,"passed_time":71.84677483,"remaining_time":391.6808047},
{"learn":[0.9870838299],"iteration":155,"passed_time":72.22258627,"remaining_time":390.7427103},
{"learn":[0.9854599269],"iteration":156,"passed_time":72.76720726,"remaining_time":390.7181893},
{"learn":[0.98222121],"iteration":157,"passed_time":73.22998359,"remaining_time":390.2509252},
{"learn":[0.9797283995],"iteration":158,"passed_time":73.74837082,"remaining_time":390.0778607},
{"learn":[0.9785589706],"iteration":159,"passed_time":74.22759601,"remaining_time":389.694879},
{"learn":[0.9762689067],"iteration":160,"passed_time":74.69955814,"remaining_time":389.2728527},
{"learn":[0.9758781852],"iteration":161,"passed_time":75.18311989,"remaining_time":388.9102127},
{"learn":[0.9742867947],"iteration":162,"passed_time":75.65642914,"remaining_time":388.4934429},
{"learn":[0.9719308091],"iteration":163,"passed_time":76.07365692,"remaining_time":387.7901048},
{"learn":[0.9692970007],"iteration":164,"passed_time":76.54383785,"remaining_time":387.3582097},
{"learn":[0.965914925],"iteration":165,"passed_time":77.00520755,"remaining_time":386.8815849},
{"learn":[0.9633562379],"iteration":166,"passed_time":77.4772631,"remaining_time":386.4584441},
{"learn":[0.9617278623],"iteration":167,"passed_time":77.98245229,"remaining_time":386.1988113},
{"learn":[0.9610749058],"iteration":168,"passed_time":78.49519742,"remaining_time":385.9734264},
{"learn":[0.9589970571],"iteration":169,"passed_time":78.96451873,"remaining_time":385.5326502},
{"learn":[0.9572790624],"iteration":170,"passed_time":79.45615065,"remaining_time":385.1997011},
{"learn":[0.9557326023],"iteration":171,"passed_time":79.92196863,"remaining_time":384.7406397},
{"learn":[0.9543721755],"iteration":172,"passed_time":80.36574507,"remaining_time":384.176134},
{"learn":[0.9519807605],"iteration":173,"passed_time":80.84160246,"remaining_time":383.7653082},
{"learn":[0.9513302569],"iteration":174,"passed_time":81.29534133,"remaining_time":383.2494663},
{"learn":[0.9510178754],"iteration":175,"passed_time":81.75284947,"remaining_time":382.751977},
{"learn":[0.9499965812],"iteration":176,"passed_time":82.23197678,"remaining_time":382.3554626},
{"learn":[0.9469143326],"iteration":177,"passed_time":82.75393065,"remaining_time":382.1557921},
{"learn":[0.9443669518],"iteration":178,"passed_time":83.27410853,"remaining_time":381.9443749},
{"learn":[0.9433803573],"iteration":179,"passed_time":83.81111662,"remaining_time":381.8061979},
{"learn":[0.9413335808],"iteration":180,"passed_time":84.29318194,"remaining_time":381.4150056},
{"learn":[0.9406186405],"iteration":181,"passed_time":84.73859218,"remaining_time":380.8580681},
{"learn":[0.9383790103],"iteration":182,"passed_time":85.20963401,"remaining_time":380.4167814},
{"learn":[0.9339116082],"iteration":183,"passed_time":85.65094055,"remaining_time":379.8433016},
{"learn":[0.9306712783],"iteration":184,"passed_time":86.1416599,"remaining_time":379.4889342},
{"learn":[0.9285034786],"iteration":185,"passed_time":86.57412607,"remaining_time":378.8781646},
{"learn":[0.9271894123],"iteration":186,"passed_time":87.05937588,"remaining_time":378.4987839},
{"learn":[0.9235795404],"iteration":187,"passed_time":87.55944303,"remaining_time":378.1822752},
{"learn":[0.9225096658],"iteration":188,"passed_time":88.01206299,"remaining_time":377.660228},
{"learn":[0.9193476523],"iteration":189,"passed_time":88.45917887,"remaining_time":377.1154467},
{"learn":[0.9166989687],"iteration":190,"passed_time":88.91241629,"remaining_time":376.5976166},
{"learn":[0.9154397326],"iteration":191,"passed_time":89.40263109,"remaining_time":376.2360725},
{"learn":[0.913819631],"iteration":192,"passed_time":89.87963864,"remaining_time":375.8179709},
{"learn":[0.9110715665],"iteration":193,"passed_time":90.35045687,"remaining_time":375.3735476},
{"learn":[0.9095574499],"iteration":194,"passed_time":90.81319001,"remaining_time":374.8954767},
{"learn":[0.9092229244],"iteration":195,"passed_time":91.31003791,"remaining_time":374.5575024},
{"learn":[0.9076139136],"iteration":196,"passed_time":91.76631099,"remaining_time":374.0525265},
{"learn":[0.9053917592],"iteration":197,"passed_time":92.22109246,"remaining_time":373.5420008},
{"learn":[0.9034085942],"iteration":198,"passed_time":92.67116565,"remaining_time":373.0130838},
{"learn":[0.9017352744],"iteration":199,"passed_time":93.12930355,"remaining_time":372.5172142},
{"learn":[0.8970641455],"iteration":200,"passed_time":93.56043812,"remaining_time":371.9143784},
{"learn":[0.8951932916],"iteration":201,"passed_time":94.01387456,"remaining_time":371.401346},
{"learn":[0.8931936316],"iteration":202,"passed_time":94.45423585,"remaining_time":370.8375664},
{"learn":[0.888050819],"iteration":203,"passed_time":94.95439362,"remaining_time":370.5083202},
{"learn":[0.8859065917],"iteration":204,"passed_time":95.44501085,"remaining_time":370.1404079},
{"learn":[0.8849481581],"iteration":205,"passed_time":95.90393171,"remaining_time":369.6491349},
{"learn":[0.88428052],"iteration":206,"passed_time":96.36478936,"remaining_time":369.165594},
{"learn":[0.8820744809],"iteration":207,"passed_time":96.82136266,"remaining_time":368.6659578},
{"learn":[0.880565828],"iteration":208,"passed_time":97.27055309,"remaining_time":368.1387918},
{"learn":[0.8795455737],"iteration":209,"passed_time":97.7781477,"remaining_time":367.8320795},
{"learn":[0.8782613968],"iteration":210,"passed_time":98.25251226,"remaining_time":367.3992046},
{"learn":[0.8767019543],"iteration":211,"passed_time":98.70056582,"remaining_time":366.8681409},
{"learn":[0.8748431932],"iteration":212,"passed_time":99.16002482,"remaining_time":366.3799978},
{"learn":[0.8742029089],"iteration":213,"passed_time":99.66144527,"remaining_time":366.0462429},
{"learn":[0.8736267851],"iteration":214,"passed_time":100.1505571,"remaining_time":365.6659875},
{"learn":[0.8717503362],"iteration":215,"passed_time":100.6658818,"remaining_time":365.3798672},
{"learn":[0.8710307759],"iteration":216,"passed_time":101.1923346,"remaining_time":365.1317881},
{"learn":[0.8694785367],"iteration":217,"passed_time":101.7155871,"remaining_time":364.869675},
{"learn":[0.8680643525],"iteration":218,"passed_time":102.1741492,"remaining_time":364.3744773},
{"learn":[0.8657819853],"iteration":219,"passed_time":102.6551772,"remaining_time":363.9592645},
{"learn":[0.864267296],"iteration":220,"passed_time":103.1197707,"remaining_time":363.4855267},
{"learn":[0.8619451426],"iteration":221,"passed_time":103.6312201,"remaining_time":363.1760776},
{"learn":[0.8601613016],"iteration":222,"passed_time":104.1495683,"remaining_time":362.8888546},
{"learn":[0.8580257459],"iteration":223,"passed_time":104.7090806,"remaining_time":362.7421721},
{"learn":[0.857769546],"iteration":224,"passed_time":105.2130583,"remaining_time":362.400534},
{"learn":[0.8569847123],"iteration":225,"passed_time":105.7600138,"remaining_time":362.2046491},
{"learn":[0.8560519817],"iteration":226,"passed_time":106.2150882,"remaining_time":361.6927893},
{"learn":[0.8541181541],"iteration":227,"passed_time":106.6698987,"remaining_time":361.1805342},
{"learn":[0.8495077453],"iteration":228,"passed_time":107.1490961,"remaining_time":360.750887},
{"learn":[0.848632247],"iteration":229,"passed_time":107.6849731,"remaining_time":360.5105622},
{"learn":[0.8468306122],"iteration":230,"passed_time":108.1696838,"remaining_time":360.0973457},
{"learn":[0.8451230291],"iteration":231,"passed_time":108.6372307,"remaining_time":359.6266946},
{"learn":[0.8440988868],"iteration":232,"passed_time":109.0930155,"remaining_time":359.1173514},
{"learn":[0.8424340826],"iteration":233,"passed_time":109.5721434,"remaining_time":358.6848796},
{"learn":[0.8410354509],"iteration":234,"passed_time":110.0400717,"remaining_time":358.2155525},
{"learn":[0.8395427094],"iteration":235,"passed_time":110.481298,"remaining_time":357.6597954},
{"learn":[0.8386633845],"iteration":236,"passed_time":110.9538336,"remaining_time":357.205802},
{"learn":[0.8384872911],"iteration":237,"passed_time":111.4807997,"remaining_time":356.9259217},
{"learn":[0.8380369186],"iteration":238,"passed_time":111.9412394,"remaining_time":356.4321474},
{"learn":[0.8375927382],"iteration":239,"passed_time":112.4228736,"remaining_time":356.0057663},
{"learn":[0.8353913289],"iteration":240,"passed_time":112.878373,"remaining_time":355.4966187},
{"learn":[0.8348098346],"iteration":241,"passed_time":113.3430482,"remaining_time":355.016655},
{"learn":[0.8330744716],"iteration":242,"passed_time":113.7983731,"remaining_time":354.5076889},
{"learn":[0.8316493525],"iteration":243,"passed_time":114.2289823,"remaining_time":353.9225846},
{"learn":[0.8309663487],"iteration":244,"passed_time":114.7134645,"remaining_time":353.5047579},
{"learn":[0.8260831323],"iteration":245,"passed_time":115.1775022,"remaining_time":353.0237263},
{"learn":[0.8254234581],"iteration":246,"passed_time":115.6761692,"remaining_time":352.6484024},
{"learn":[0.8247143859],"iteration":247,"passed_time":116.1619456,"remaining_time":352.2329964},
{"learn":[0.8229836475],"iteration":248,"passed_time":116.6585335,"remaining_time":351.8496332},
{"learn":[0.8220356831],"iteration":249,"passed_time":117.1542751,"remaining_time":351.4628252},
{"learn":[0.8215010842],"iteration":250,"passed_time":117.6259626,"remaining_time":351.0033705},
{"learn":[0.8214390116],"iteration":251,"passed_time":118.0285381,"remaining_time":350.3386765},
{"learn":[0.8192951963],"iteration":252,"passed_time":118.5106224,"remaining_time":349.91081},
{"learn":[0.8188231038],"iteration":253,"passed_time":119.0631258,"remaining_time":349.6893378},
{"learn":[0.8170978453],"iteration":254,"passed_time":119.5659208,"remaining_time":349.3200431},
{"learn":[0.816083194],"iteration":255,"passed_time":120.0449413,"remaining_time":348.8806107},
{"learn":[0.8157836328],"iteration":256,"passed_time":120.4971498,"remaining_time":348.3633552},
{"learn":[0.8142458759],"iteration":257,"passed_time":120.9824331,"remaining_time":347.9417263},
{"learn":[0.8114512787],"iteration":258,"passed_time":121.4502928,"remaining_time":347.4697568},
{"learn":[0.8107533396],"iteration":259,"passed_time":121.9250522,"remaining_time":347.0174562},
{"learn":[0.8081478545],"iteration":260,"passed_time":122.4445534,"remaining_time":346.6916665},
{"learn":[0.8068722167],"iteration":261,"passed_time":122.9290788,"remaining_time":346.2658784},
{"learn":[0.8058224098],"iteration":262,"passed_time":123.3772241,"remaining_time":345.7376966},
{"learn":[0.8054039487],"iteration":263,"passed_time":123.9043505,"remaining_time":345.4303105},
{"learn":[0.8038528832],"iteration":264,"passed_time":124.3991584,"remaining_time":345.031628},
{"learn":[0.8034059495],"iteration":265,"passed_time":124.8907785,"remaining_time":344.6234264},
{"learn":[0.8030066359],"iteration":266,"passed_time":125.3276209,"remaining_time":344.0642176},
{"learn":[0.8027745421],"iteration":267,"passed_time":125.7519277,"remaining_time":343.4716832},
{"learn":[0.8016477717],"iteration":268,"passed_time":126.2206927,"remaining_time":343.0012133},
{"learn":[0.8012059908],"iteration":269,"passed_time":126.6237813,"remaining_time":342.3531865},
{"learn":[0.7990512103],"iteration":270,"passed_time":127.0933868,"remaining_time":341.8859004},
{"learn":[0.7979173483],"iteration":271,"passed_time":127.5465426,"remaining_time":341.37457},
{"learn":[0.7957978645],"iteration":272,"passed_time":128.0635451,"remaining_time":341.0336896},
{"learn":[0.7949925195],"iteration":273,"passed_time":128.5652088,"remaining_time":340.6508816},
{"learn":[0.7947009717],"iteration":274,"passed_time":129.0900767,"remaining_time":340.3283842},
{"learn":[0.7937595496],"iteration":275,"passed_time":129.6461517,"remaining_time":340.0862821},
{"learn":[0.7918810181],"iteration":276,"passed_time":130.117419,"remaining_time":339.6205557},
{"learn":[0.7913807362],"iteration":277,"passed_time":130.6020824,"remaining_time":339.1895809},
{"learn":[0.7904111483],"iteration":278,"passed_time":131.0475127,"remaining_time":338.6568339},
{"learn":[0.7893335545],"iteration":279,"passed_time":131.5512353,"remaining_time":338.274605},
{"learn":[0.7872368125],"iteration":280,"passed_time":132.0080533,"remaining_time":337.7714957},
{"learn":[0.7865782149],"iteration":281,"passed_time":132.4644707,"remaining_time":337.2676949},
{"learn":[0.78636423],"iteration":282,"passed_time":132.9898811,"remaining_time":336.9390274},
{"learn":[0.7861423738],"iteration":283,"passed_time":133.4859909,"remaining_time":336.5351039},
{"learn":[0.7853046787],"iteration":284,"passed_time":133.9937669,"remaining_time":336.1598013},
{"learn":[0.784400042],"iteration":285,"passed_time":134.4370571,"remaining_time":335.6225831},
{"learn":[0.783448054],"iteration":286,"passed_time":134.869725,"remaining_time":335.0596304},
{"learn":[0.7819252663],"iteration":287,"passed_time":135.3443053,"remaining_time":334.6011992},
{"learn":[0.7817562008],"iteration":288,"passed_time":135.8167414,"remaining_time":334.137381},
{"learn":[0.7812454114],"iteration":289,"passed_time":136.316744,"remaining_time":333.7409938},
{"learn":[0.779819962],"iteration":290,"passed_time":136.7849472,"remaining_time":333.2664176},
{"learn":[0.7795600008],"iteration":291,"passed_time":137.2647291,"remaining_time":332.8199595},
{"learn":[0.7782873414],"iteration":292,"passed_time":137.7276043,"remaining_time":332.3324787},
{"learn":[0.7767196873],"iteration":293,"passed_time":138.1867104,"remaining_time":331.8361141},
{"learn":[0.7747706659],"iteration":294,"passed_time":138.7017592,"remaining_time":331.4736957},
{"learn":[0.773448697],"iteration":295,"passed_time":139.1620523,"remaining_time":330.9800163},
{"learn":[0.7699617836],"iteration":296,"passed_time":139.626036,"remaining_time":330.4952972},
{"learn":[0.7695556883],"iteration":297,"passed_time":140.0822074,"remaining_time":329.992314},
{"learn":[0.7686803364],"iteration":298,"passed_time":140.5113305,"remaining_time":329.4262296},
{"learn":[0.76777628],"iteration":299,"passed_time":140.9666271,"remaining_time":328.9221299},
{"learn":[0.7651868901],"iteration":300,"passed_time":141.4463606,"remaining_time":328.4751033},
{"learn":[0.7615373364],"iteration":301,"passed_time":141.9253165,"remaining_time":328.0260626},
{"learn":[0.7603638703],"iteration":302,"passed_time":142.3996734,"remaining_time":327.5662455},
{"learn":[0.7594560827],"iteration":303,"passed_time":142.8671482,"remaining_time":327.0905762},
{"learn":[0.7591042318],"iteration":304,"passed_time":143.3375368,"remaining_time":326.6216002},
{"learn":[0.7578422004],"iteration":305,"passed_time":143.8235493,"remaining_time":326.1880498},
{"learn":[0.7574240215],"iteration":306,"passed_time":144.3713523,"remaining_time":325.893639},
{"learn":[0.7559078778],"iteration":307,"passed_time":144.8581843,"remaining_time":325.460596},
{"learn":[0.7548957378],"iteration":308,"passed_time":145.3108566,"remaining_time":324.9508153},
{"learn":[0.7541042364],"iteration":309,"passed_time":145.7519303,"remaining_time":324.4155869},
{"learn":[0.7530852087],"iteration":310,"passed_time":146.1815411,"remaining_time":323.8555685},
{"learn":[0.7519823699],"iteration":311,"passed_time":146.676889,"remaining_time":323.441345},
{"learn":[0.7510732472],"iteration":312,"passed_time":147.153655,"remaining_time":322.9858178},
{"learn":[0.7482071695],"iteration":313,"passed_time":147.6439988,"remaining_time":322.559819},
{"learn":[0.7474118333],"iteration":314,"passed_time":148.1237601,"remaining_time":322.1103989},
{"learn":[0.7453251441],"iteration":315,"passed_time":148.6023672,"remaining_time":321.6582886},
{"learn":[0.7434586523],"iteration":316,"passed_time":149.104034,"remaining_time":321.2556948},
{"learn":[0.743342878],"iteration":317,"passed_time":149.561721,"remaining_time":320.7581565},
{"learn":[0.7432427263],"iteration":318,"passed_time":150.0732461,"remaining_time":320.3758013},
{"learn":[0.7424323782],"iteration":319,"passed_time":150.5402295,"remaining_time":319.8979878},
{"learn":[0.7415372199],"iteration":320,"passed_time":151.0298833,"remaining_time":319.4681955},
{"learn":[0.7405364581],"iteration":321,"passed_time":151.5273235,"remaining_time":319.0544265},
{"learn":[0.7398595532],"iteration":322,"passed_time":151.9526877,"remaining_time":318.48907},
{"learn":[0.7379727582],"iteration":323,"passed_time":152.4298511,"remaining_time":318.0326524},
{"learn":[0.7376218552],"iteration":324,"passed_time":152.870761,"remaining_time":317.5008113},
{"learn":[0.7371533142],"iteration":325,"passed_time":153.3513612,"remaining_time":317.0515874},
{"learn":[0.7367566087],"iteration":326,"passed_time":153.8451823,"remaining_time":316.6293814},
{"learn":[0.7360334269],"iteration":327,"passed_time":154.3194083,"remaining_time":316.1665926},
{"learn":[0.7353734416],"iteration":328,"passed_time":154.8201064,"remaining_time":315.7577246},
{"learn":[0.7343704267],"iteration":329,"passed_time":155.2781378,"remaining_time":315.2616737},
{"learn":[0.7335293804],"iteration":330,"passed_time":155.7561404,"remaining_time":314.8062173},
{"learn":[0.732927937],"iteration":331,"passed_time":156.2249441,"remaining_time":314.3321164},
{"learn":[0.7322510747],"iteration":332,"passed_time":156.6885546,"remaining_time":313.8476454},
{"learn":[0.7312744585],"iteration":333,"passed_time":157.1386221,"remaining_time":313.3362944},
{"learn":[0.730993255],"iteration":334,"passed_time":157.6651994,"remaining_time":312.9771868},
{"learn":[0.7273910105],"iteration":335,"passed_time":158.1719091,"remaining_time":312.5778203},
{"learn":[0.7265836696],"iteration":336,"passed_time":158.6233842,"remaining_time":312.0691506},
{"learn":[0.7258297195],"iteration":337,"passed_time":159.1158406,"remaining_time":311.6410843},
{"learn":[0.72376417],"iteration":338,"passed_time":159.5355293,"remaining_time":311.0707518},
{"learn":[0.7230225711],"iteration":339,"passed_time":160.0006395,"remaining_time":310.5894766},
{"learn":[0.7223414949],"iteration":340,"passed_time":160.4983651,"remaining_time":310.1713273},
{"learn":[0.7215233993],"iteration":341,"passed_time":160.952063,"remaining_time":309.6680043},
{"learn":[0.7214358923],"iteration":342,"passed_time":161.502814,"remaining_time":309.3508711},
{"learn":[0.7204881132],"iteration":343,"passed_time":161.9401609,"remaining_time":308.8161208},
{"learn":[0.7191770063],"iteration":344,"passed_time":162.5094004,"remaining_time":308.5323399},
{"learn":[0.7182916294],"iteration":345,"passed_time":162.980711,"remaining_time":308.0618064},
{"learn":[0.7176615835],"iteration":346,"passed_time":163.4443081,"remaining_time":307.5767527},
{"learn":[0.7169984781],"iteration":347,"passed_time":163.9179128,"remaining_time":307.1105723},
{"learn":[0.7160801091],"iteration":348,"passed_time":164.4173779,"remaining_time":306.6925874},
{"learn":[0.7154801094],"iteration":349,"passed_time":164.8852566,"remaining_time":306.2154766},
{"learn":[0.7153417589],"iteration":350,"passed_time":165.4134699,"remaining_time":305.8499771},
{"learn":[0.7149089524],"iteration":351,"passed_time":165.8969695,"remaining_time":305.4012393},
{"learn":[0.7143193083],"iteration":352,"passed_time":166.3661936,"remaining_time":304.9261395},
{"learn":[0.7139426595],"iteration":353,"passed_time":166.873102,"remaining_time":304.5198415},
{"learn":[0.7130679307],"iteration":354,"passed_time":167.3912238,"remaining_time":304.1333503},
{"learn":[0.712668874],"iteration":355,"passed_time":167.9033736,"remaining_time":303.7353163},
{"learn":[0.7120514663],"iteration":356,"passed_time":168.4034781,"remaining_time":303.314948},
{"learn":[0.7116982546],"iteration":357,"passed_time":168.8821245,"remaining_time":302.8556534},
{"learn":[0.7110747816],"iteration":358,"passed_time":169.3721794,"remaining_time":302.4166211},
{"learn":[0.7104872543],"iteration":359,"passed_time":169.9040994,"remaining_time":302.0517323},
{"learn":[0.7097925378],"iteration":360,"passed_time":170.3418736,"remaining_time":301.519272},
{"learn":[0.7030469532],"iteration":361,"passed_time":170.8317138,"remaining_time":301.0790977},
{"learn":[0.7023613337],"iteration":362,"passed_time":171.3404837,"remaining_time":300.6718681},
{"learn":[0.7012257628],"iteration":363,"passed_time":171.8039298,"remaining_time":300.1848883},
{"learn":[0.7003796259],"iteration":364,"passed_time":172.2323245,"remaining_time":299.6370577},
{"learn":[0.7000894295],"iteration":365,"passed_time":172.6950572,"remaining_time":299.1493613},
{"learn":[0.6960538779],"iteration":366,"passed_time":173.1430376,"remaining_time":298.6363565},
{"learn":[0.6957469865],"iteration":367,"passed_time":173.6464231,"remaining_time":298.218857},
{"learn":[0.6951557951],"iteration":368,"passed_time":174.1372126,"remaining_time":297.7793526},
{"learn":[0.6949855871],"iteration":369,"passed_time":174.6613536,"remaining_time":297.3963589},
{"learn":[0.6945067148],"iteration":370,"passed_time":175.1207531,"remaining_time":296.9028401},
{"learn":[0.6937263788],"iteration":371,"passed_time":175.5961794,"remaining_time":296.4365609},
{"learn":[0.6934847859],"iteration":372,"passed_time":176.0483784,"remaining_time":295.9311883},
{"learn":[0.6929325014],"iteration":373,"passed_time":176.4893295,"remaining_time":295.4072735},
{"learn":[0.692139756],"iteration":374,"passed_time":176.9883761,"remaining_time":294.9806268},
{"learn":[0.6916916301],"iteration":375,"passed_time":177.4715971,"remaining_time":294.5273314},
{"learn":[0.6910186818],"iteration":376,"passed_time":177.9802052,"remaining_time":294.1158298},
{"learn":[0.6885206384],"iteration":377,"passed_time":178.4306802,"remaining_time":293.6081564},
{"learn":[0.6883235511],"iteration":378,"passed_time":178.9249263,"remaining_time":293.1725045},
{"learn":[0.688088597],"iteration":379,"passed_time":179.422123,"remaining_time":292.7413585},
{"learn":[0.6875882625],"iteration":380,"passed_time":179.9105073,"remaining_time":292.2955486},
{"learn":[0.6860444276],"iteration":381,"passed_time":180.3520368,"remaining_time":291.773714},
{"learn":[0.6855843356],"iteration":382,"passed_time":180.7981989,"remaining_time":291.2597617},
{"learn":[0.6849475919],"iteration":383,"passed_time":181.2404646,"remaining_time":290.739912},
{"learn":[0.6841170754],"iteration":384,"passed_time":181.7194005,"remaining_time":290.2790424},
{"learn":[0.683024729],"iteration":385,"passed_time":182.157747,"remaining_time":289.7535146},
{"learn":[0.6824089383],"iteration":386,"passed_time":182.6320107,"remaining_time":289.2853296},
{"learn":[0.6816314461],"iteration":387,"passed_time":183.1293449,"remaining_time":288.8535028},
{"learn":[0.6806263374],"iteration":388,"passed_time":183.6028144,"remaining_time":288.383855},
{"learn":[0.6800915952],"iteration":389,"passed_time":184.0197417,"remaining_time":287.8257499},
{"learn":[0.6780936519],"iteration":390,"passed_time":184.4697246,"remaining_time":287.3198524},
{"learn":[0.6774749395],"iteration":391,"passed_time":184.9080737,"remaining_time":286.7961959},
{"learn":[0.6771287541],"iteration":392,"passed_time":185.3855526,"remaining_time":286.3334108},
{"learn":[0.6768360097],"iteration":393,"passed_time":185.8832958,"remaining_time":285.9017189},
{"learn":[0.6763336133],"iteration":394,"passed_time":186.3177426,"remaining_time":285.372745},
{"learn":[0.6760684472],"iteration":395,"passed_time":186.8013137,"remaining_time":284.9191755},
{"learn":[0.6756221092],"iteration":396,"passed_time":187.3038897,"remaining_time":284.4943211},
{"learn":[0.67501837],"iteration":397,"passed_time":187.7813422,"remaining_time":284.0310754},
{"learn":[0.6738430003],"iteration":398,"passed_time":188.2548124,"remaining_time":283.5617601},
{"learn":[0.6733644444],"iteration":399,"passed_time":188.7467753,"remaining_time":283.120163},
{"learn":[0.6730608615],"iteration":400,"passed_time":189.244119,"remaining_time":282.6863523},
{"learn":[0.6722473371],"iteration":401,"passed_time":189.7291212,"remaining_time":282.2338668},
{"learn":[0.6720936262],"iteration":402,"passed_time":190.2261272,"remaining_time":281.7990023},
{"learn":[0.6713973955],"iteration":403,"passed_time":190.7159965,"remaining_time":281.3533018},
{"learn":[0.6707372966],"iteration":404,"passed_time":191.1965894,"remaining_time":280.8937548},
{"learn":[0.670182463],"iteration":405,"passed_time":191.6984241,"remaining_time":280.465182},
{"learn":[0.6693790316],"iteration":406,"passed_time":192.1639611,"remaining_time":279.9833635},
{"learn":[0.6690463267],"iteration":407,"passed_time":192.600241,"remaining_time":279.4591732},
{"learn":[0.6686373769],"iteration":408,"passed_time":193.0950434,"remaining_time":279.0199771},
{"learn":[0.6680077305],"iteration":409,"passed_time":193.5549613,"remaining_time":278.5303102},
{"learn":[0.6674002374],"iteration":410,"passed_time":194.0457323,"remaining_time":278.0850032},
{"learn":[0.6658400894],"iteration":411,"passed_time":194.5136886,"remaining_time":277.6069148},
{"learn":[0.6653690389],"iteration":412,"passed_time":195.0081924,"remaining_time":277.1666077},
{"learn":[0.6649073851],"iteration":413,"passed_time":195.5021783,"remaining_time":276.7253055},
{"learn":[0.6630159037],"iteration":414,"passed_time":195.9761802,"remaining_time":276.2555793},
{"learn":[0.6629120734],"iteration":415,"passed_time":196.4548621,"remaining_time":275.7924026},
{"learn":[0.6620905997],"iteration":416,"passed_time":196.9356344,"remaining_time":275.3320741},
{"learn":[0.6616662328],"iteration":417,"passed_time":197.4221473,"remaining_time":274.8796405},
{"learn":[0.6610603923],"iteration":418,"passed_time":197.8598675,"remaining_time":274.3593866},
{"learn":[0.6606453997],"iteration":419,"passed_time":198.2956753,"remaining_time":273.836885},
{"learn":[0.660183308],"iteration":420,"passed_time":198.7887636,"remaining_time":273.3935728},
{"learn":[0.6590317487],"iteration":421,"passed_time":199.2573981,"remaining_time":272.916531},
{"learn":[0.6585998923],"iteration":422,"passed_time":199.680375,"remaining_time":272.3772491},
{"learn":[0.6575165588],"iteration":423,"passed_time":200.1577736,"remaining_time":271.9124471},
{"learn":[0.6571145421],"iteration":424,"passed_time":200.6439773,"remaining_time":271.4594987},
{"learn":[0.6565433539],"iteration":425,"passed_time":201.111391,"remaining_time":270.9810761},
{"learn":[0.6561820681],"iteration":426,"passed_time":201.5896312,"remaining_time":270.5172335},
{"learn":[0.6559614808],"iteration":427,"passed_time":202.0323867,"remaining_time":270.0059},
{"learn":[0.6554699554],"iteration":428,"passed_time":202.4263522,"remaining_time":269.4299466},
{"learn":[0.6549361561],"iteration":429,"passed_time":202.8981237,"remaining_time":268.9579779},
{"learn":[0.6542176305],"iteration":430,"passed_time":203.3321401,"remaining_time":268.4361665},
{"learn":[0.6533583514],"iteration":431,"passed_time":203.8243169,"remaining_time":267.9912315},
{"learn":[0.6532103527],"iteration":432,"passed_time":204.3544918,"remaining_time":267.5958357},
{"learn":[0.6531183447],"iteration":433,"passed_time":204.8582828,"remaining_time":267.1654102},
{"learn":[0.6529913565],"iteration":434,"passed_time":205.3743595,"remaining_time":266.7506049},
{"learn":[0.6510470132],"iteration":435,"passed_time":205.8271773,"remaining_time":266.2535046},
{"learn":[0.6506071999],"iteration":436,"passed_time":206.2741682,"remaining_time":265.7491001},
{"learn":[0.6502827147],"iteration":437,"passed_time":206.7527246,"remaining_time":265.2854595},
{"learn":[0.6494742856],"iteration":438,"passed_time":207.2656859,"remaining_time":264.8657171},
{"learn":[0.648944324],"iteration":439,"passed_time":207.7381656,"remaining_time":264.3940289},
{"learn":[0.6480648851],"iteration":440,"passed_time":208.1987655,"remaining_time":263.9072787},
{"learn":[0.6475651229],"iteration":441,"passed_time":208.6913253,"remaining_time":263.4609943},
{"learn":[0.6471717054],"iteration":442,"passed_time":209.1216245,"remaining_time":262.9362186},
{"learn":[0.6467072508],"iteration":443,"passed_time":209.5628908,"remaining_time":262.425602},
{"learn":[0.6460975965],"iteration":444,"passed_time":210.0364711,"remaining_time":261.9555988},
{"learn":[0.6457760319],"iteration":445,"passed_time":210.5214649,"remaining_time":261.4997569},
{"learn":[0.6448335266],"iteration":446,"passed_time":210.9830844,"remaining_time":261.0148672},
{"learn":[0.6445981322],"iteration":447,"passed_time":211.4650565,"remaining_time":260.5551589},
{"learn":[0.6439064443],"iteration":448,"passed_time":211.9765668,"remaining_time":260.1315998},
{"learn":[0.6433164939],"iteration":449,"passed_time":212.4683527,"remaining_time":259.6835422},
{"learn":[0.6429117142],"iteration":450,"passed_time":212.9754155,"remaining_time":259.2538871},
{"learn":[0.6424925697],"iteration":451,"passed_time":213.4324091,"remaining_time":258.7631863},
{"learn":[0.6417850767],"iteration":452,"passed_time":213.9130501,"remaining_time":258.3011885},
{"learn":[0.6414755404],"iteration":453,"passed_time":214.360835,"remaining_time":257.7995945},
{"learn":[0.6413794888],"iteration":454,"passed_time":214.7947579,"remaining_time":257.2816331},
{"learn":[0.6408788606],"iteration":455,"passed_time":215.2333752,"remaining_time":256.7696406},
{"learn":[0.6403604194],"iteration":456,"passed_time":215.709194,"remaining_time":256.3021715},
{"learn":[0.6401158466],"iteration":457,"passed_time":216.1591105,"remaining_time":255.8040128},
{"learn":[0.6396110374],"iteration":458,"passed_time":216.6163706,"remaining_time":255.31472},
{"learn":[0.6392686308],"iteration":459,"passed_time":217.095816,"remaining_time":254.8516101},
{"learn":[0.6385534585],"iteration":460,"passed_time":217.5867365,"remaining_time":254.4018459},
{"learn":[0.637559518],"iteration":461,"passed_time":218.0242192,"remaining_time":253.8896752},
{"learn":[0.6341883659],"iteration":462,"passed_time":218.4804269,"remaining_time":253.3995448},
{"learn":[0.6335810577],"iteration":463,"passed_time":218.9624648,"remaining_time":252.939399},
{"learn":[0.6333669625],"iteration":464,"passed_time":219.4530309,"remaining_time":252.4889711},
{"learn":[0.6314652902],"iteration":465,"passed_time":219.9136996,"remaining_time":252.0041107},
{"learn":[0.6311373076],"iteration":466,"passed_time":220.3891221,"remaining_time":251.5361929},
{"learn":[0.6303732553],"iteration":467,"passed_time":220.9412297,"remaining_time":251.155415},
{"learn":[0.6301534737],"iteration":468,"passed_time":221.4697357,"remaining_time":250.7471848},
{"learn":[0.6299348049],"iteration":469,"passed_time":221.9399606,"remaining_time":250.2727215},
{"learn":[0.629426825],"iteration":470,"passed_time":222.4207538,"remaining_time":249.810146},
{"learn":[0.6280750858],"iteration":471,"passed_time":222.8906525,"remaining_time":249.3353062},
{"learn":[0.627253844],"iteration":472,"passed_time":223.4358498,"remaining_time":248.9443824},
{"learn":[0.6255819683],"iteration":473,"passed_time":223.8929471,"remaining_time":248.4550425},
{"learn":[0.6250490013],"iteration":474,"passed_time":224.3460989,"remaining_time":247.9614778},
{"learn":[0.6245713778],"iteration":475,"passed_time":224.8654638,"remaining_time":247.5409727},
{"learn":[0.6238519142],"iteration":476,"passed_time":225.327851,"remaining_time":247.0575809},
{"learn":[0.6233289209],"iteration":477,"passed_time":225.7881329,"remaining_time":246.5719778},
{"learn":[0.6227811308],"iteration":478,"passed_time":226.2594102,"remaining_time":246.0984399},
{"learn":[0.622341249],"iteration":479,"passed_time":226.7099585,"remaining_time":245.6024551},
{"learn":[0.6218627998],"iteration":480,"passed_time":227.2008182,"remaining_time":245.1501552},
{"learn":[0.6213946352],"iteration":481,"passed_time":227.6744354,"remaining_time":244.679165},
{"learn":[0.6210106605],"iteration":482,"passed_time":228.1318985,"remaining_time":244.1908727},
{"learn":[0.6196287487],"iteration":483,"passed_time":228.600026,"remaining_time":243.7140773},
{"learn":[0.6188655951],"iteration":484,"passed_time":229.0512315,"remaining_time":243.2193489},
{"learn":[0.6187615369],"iteration":485,"passed_time":229.5444114,"remaining_time":242.7691923},
{"learn":[0.6182890822],"iteration":486,"passed_time":230.0130802,"remaining_time":242.2930393},
{"learn":[0.618140321],"iteration":487,"passed_time":230.4635194,"remaining_time":241.7977909},
{"learn":[0.6179877348],"iteration":488,"passed_time":230.9697511,"remaining_time":241.3610283},
{"learn":[0.617532781],"iteration":489,"passed_time":231.4185777,"remaining_time":240.8642339},
{"learn":[0.6172561898],"iteration":490,"passed_time":231.8912298,"remaining_time":240.3923339},
{"learn":[0.6170150275],"iteration":491,"passed_time":232.3637576,"remaining_time":239.9203026},
{"learn":[0.6160583319],"iteration":492,"passed_time":232.8549116,"remaining_time":239.4674243},
{"learn":[0.6153693186],"iteration":493,"passed_time":233.3105321,"remaining_time":238.9779944},
{"learn":[0.6145205527],"iteration":494,"passed_time":233.8463042,"remaining_time":238.570472},
{"learn":[0.6142901322],"iteration":495,"passed_time":234.3642761,"remaining_time":238.1443451},
{"learn":[0.6139850085],"iteration":496,"passed_time":234.870546,"remaining_time":237.7060053},
{"learn":[0.6135577803],"iteration":497,"passed_time":235.4381,"remaining_time":237.329169},
{"learn":[0.6131362831],"iteration":498,"passed_time":235.9540476,"remaining_time":236.8997552},
{"learn":[0.6125583127],"iteration":499,"passed_time":236.4558067,"remaining_time":236.4558067},
{"learn":[0.6122528496],"iteration":500,"passed_time":236.9666908,"remaining_time":236.020716},
{"learn":[0.6121570422],"iteration":501,"passed_time":237.4939368,"remaining_time":235.6015548},
{"learn":[0.6115662439],"iteration":502,"passed_time":237.9743671,"remaining_time":235.1357066},
{"learn":[0.6102333913],"iteration":503,"passed_time":238.4353213,"remaining_time":234.6506337},
{"learn":[0.6099598898],"iteration":504,"passed_time":238.9435034,"remaining_time":234.2119489},
{"learn":[0.6075596986],"iteration":505,"passed_time":239.4356496,"remaining_time":233.7573338},
{"learn":[0.6073509748],"iteration":506,"passed_time":239.9278149,"remaining_time":233.3025893},
{"learn":[0.6070287738],"iteration":507,"passed_time":240.3867316,"remaining_time":232.815496},
{"learn":[0.6069180601],"iteration":508,"passed_time":240.8331295,"remaining_time":232.3164373},
{"learn":[0.6062800149],"iteration":509,"passed_time":241.3292668,"remaining_time":231.865374},
{"learn":[0.6055269325],"iteration":510,"passed_time":241.7678295,"remaining_time":231.3590384},
{"learn":[0.605008986],"iteration":511,"passed_time":242.1927621,"remaining_time":230.8399764},
{"learn":[0.6049475734],"iteration":512,"passed_time":242.6976609,"remaining_time":230.3971946},
{"learn":[0.6043118167],"iteration":513,"passed_time":243.1666118,"remaining_time":229.9201816},
{"learn":[0.6037182301],"iteration":514,"passed_time":243.6411018,"remaining_time":229.4484163},
{"learn":[0.6034987947],"iteration":515,"passed_time":244.1086453,"remaining_time":228.9701247},
{"learn":[0.602922279],"iteration":516,"passed_time":244.5713457,"remaining_time":228.48735},
{"learn":[0.602632753],"iteration":517,"passed_time":245.0462764,"remaining_time":228.0160332},
{"learn":[0.6023489693],"iteration":518,"passed_time":245.5418964,"remaining_time":227.5638771},
{"learn":[0.6021057559],"iteration":519,"passed_time":246.0088526,"remaining_time":227.0850947},
{"learn":[0.6011826125],"iteration":520,"passed_time":246.5016575,"remaining_time":226.6301227},
{"learn":[0.6007694897],"iteration":521,"passed_time":246.978714,"remaining_time":226.1605848},
{"learn":[0.6004873212],"iteration":522,"passed_time":247.5030536,"remaining_time":225.7341425},
{"learn":[0.5997246472],"iteration":523,"passed_time":247.9699322,"remaining_time":225.2551292},
{"learn":[0.5994050119],"iteration":524,"passed_time":248.4227707,"remaining_time":224.7634592},
{"learn":[0.5988660379],"iteration":525,"passed_time":248.8765611,"remaining_time":224.2727946},
{"learn":[0.5985415067],"iteration":526,"passed_time":249.3346953,"remaining_time":223.7861686},
{"learn":[0.5980718027],"iteration":527,"passed_time":249.7919286,"remaining_time":223.2988453},
{"learn":[0.5978612291],"iteration":528,"passed_time":250.2087522,"remaining_time":222.7756565},
{"learn":[0.597663395],"iteration":529,"passed_time":250.7313692,"remaining_time":222.3466859},
{"learn":[0.597267439],"iteration":530,"passed_time":251.2372681,"remaining_time":221.9025965},
{"learn":[0.597208436],"iteration":531,"passed_time":251.800298,"remaining_time":221.5085328},
{"learn":[0.5969299733],"iteration":532,"passed_time":252.3219865,"remaining_time":221.077613},
{"learn":[0.5964069215],"iteration":533,"passed_time":252.8152301,"remaining_time":220.6215304},
{"learn":[0.5962825923],"iteration":534,"passed_time":253.2812879,"remaining_time":220.1416801},
{"learn":[0.5951209111],"iteration":535,"passed_time":253.7434835,"remaining_time":219.658538},
{"learn":[0.5937685951],"iteration":536,"passed_time":254.1564716,"remaining_time":219.1330472},
{"learn":[0.5933200542],"iteration":537,"passed_time":254.6578248,"remaining_time":218.683857},
{"learn":[0.5930153698],"iteration":538,"passed_time":255.0843555,"remaining_time":218.1704785},
{"learn":[0.5926272985],"iteration":539,"passed_time":255.5598987,"remaining_time":217.699173},
{"learn":[0.5922398893],"iteration":540,"passed_time":256.0300412,"remaining_time":217.2232697},
{"learn":[0.5921760869],"iteration":541,"passed_time":256.4173791,"remaining_time":216.6774162},
{"learn":[0.5918893878],"iteration":542,"passed_time":256.8986575,"remaining_time":216.211209},
{"learn":[0.5917558343],"iteration":543,"passed_time":257.4450276,"remaining_time":215.7995085},
{"learn":[0.5915303896],"iteration":544,"passed_time":257.9186474,"remaining_time":215.3265772},
{"learn":[0.5912312456],"iteration":545,"passed_time":258.3939887,"remaining_time":214.8550748},
{"learn":[0.5910640835],"iteration":546,"passed_time":258.9159606,"remaining_time":214.4221757},
{"learn":[0.5906466471],"iteration":547,"passed_time":259.4075827,"remaining_time":213.9639186},
{"learn":[0.5903660908],"iteration":548,"passed_time":259.883966,"remaining_time":213.4930213},
{"learn":[0.5900799981],"iteration":549,"passed_time":260.3386944,"remaining_time":213.0043863},
{"learn":[0.5895959495],"iteration":550,"passed_time":260.8439854,"remaining_time":212.557077},
{"learn":[0.5889916929],"iteration":551,"passed_time":261.3237238,"remaining_time":212.0888193},
{"learn":[0.588495445],"iteration":552,"passed_time":261.7252471,"remaining_time":211.5572974},
{"learn":[0.5883107657],"iteration":553,"passed_time":262.2675439,"remaining_time":211.1395751},
{"learn":[0.5879845859],"iteration":554,"passed_time":262.7652616,"remaining_time":210.6856602},
{"learn":[0.587788514],"iteration":555,"passed_time":263.2506366,"remaining_time":210.2217314},
{"learn":[0.5874369209],"iteration":556,"passed_time":263.7469789,"remaining_time":209.7664482},
{"learn":[0.5868867118],"iteration":557,"passed_time":264.2316065,"remaining_time":209.3017384},
{"learn":[0.5867618549],"iteration":558,"passed_time":264.6815526,"remaining_time":208.809597},
{"learn":[0.5866747936],"iteration":559,"passed_time":265.1705345,"remaining_time":208.3482771},
{"learn":[0.5856275387],"iteration":560,"passed_time":265.6438562,"remaining_time":207.874604},
{"learn":[0.5854104407],"iteration":561,"passed_time":266.1160394,"remaining_time":207.400045},
{"learn":[0.5851883848],"iteration":562,"passed_time":266.5466846,"remaining_time":206.8932525},
{"learn":[0.5847471535],"iteration":563,"passed_time":266.9857847,"remaining_time":206.3932662},
{"learn":[0.5846448606],"iteration":564,"passed_time":267.4629451,"remaining_time":205.9227984},
{"learn":[0.5845231401],"iteration":565,"passed_time":267.9578149,"remaining_time":205.4658863},
{"learn":[0.5841609821],"iteration":566,"passed_time":268.4682368,"remaining_time":205.020717},
{"learn":[0.5835316781],"iteration":567,"passed_time":268.9351319,"remaining_time":204.542213},
{"learn":[0.5830658551],"iteration":568,"passed_time":269.4216804,"remaining_time":204.0786366},
{"learn":[0.5819988086],"iteration":569,"passed_time":269.8658637,"remaining_time":203.58302},
{"learn":[0.5819630784],"iteration":570,"passed_time":270.2594811,"remaining_time":203.0495927},
{"learn":[0.5816407604],"iteration":571,"passed_time":270.7396911,"remaining_time":202.5814472},
{"learn":[0.5813714648],"iteration":572,"passed_time":271.1936009,"remaining_time":202.0936607},
{"learn":[0.5811480777],"iteration":573,"passed_time":271.6827698,"remaining_time":201.6321602},
{"learn":[0.5808513388],"iteration":574,"passed_time":272.1318788,"remaining_time":201.1409539},
{"learn":[0.5804962877],"iteration":575,"passed_time":272.5923147,"remaining_time":200.6582316},
{"learn":[0.5799992328],"iteration":576,"passed_time":273.0641767,"remaining_time":200.1839632},
{"learn":[0.579688284],"iteration":577,"passed_time":273.5167849,"remaining_time":199.6956457},
{"learn":[0.5792699906],"iteration":578,"passed_time":273.9864698,"remaining_time":199.2198684},
{"learn":[0.5789304578],"iteration":579,"passed_time":274.4370103,"remaining_time":198.7302488},
{"learn":[0.5784532555],"iteration":580,"passed_time":274.9158009,"remaining_time":198.2611369},
{"learn":[0.5780762649],"iteration":581,"passed_time":275.4214808,"remaining_time":197.8113041},
{"learn":[0.5770667718],"iteration":582,"passed_time":275.9319322,"remaining_time":197.3646925},
{"learn":[0.575959242],"iteration":583,"passed_time":276.3829289,"remaining_time":196.875511},
{"learn":[0.5755413651],"iteration":584,"passed_time":276.9013905,"remaining_time":196.4343197},
{"learn":[0.5749000365],"iteration":585,"passed_time":277.3395653,"remaining_time":195.9361434},
{"learn":[0.5745076764],"iteration":586,"passed_time":277.7612856,"remaining_time":195.4265945},
{"learn":[0.5732699872],"iteration":587,"passed_time":278.1977609,"remaining_time":194.9276828},
{"learn":[0.5727216457],"iteration":588,"passed_time":278.6422131,"remaining_time":194.4345494},
{"learn":[0.5725386398],"iteration":589,"passed_time":279.0819524,"remaining_time":193.9383059},
{"learn":[0.5723637518],"iteration":590,"passed_time":279.566287,"remaining_time":193.4731157},
{"learn":[0.5715804384],"iteration":591,"passed_time":280.0467875,"remaining_time":193.0052184},
{"learn":[0.5711259647],"iteration":592,"passed_time":280.5195419,"remaining_time":192.5319621},
{"learn":[0.5708299064],"iteration":593,"passed_time":281.0106923,"remaining_time":192.0712813},
{"learn":[0.570319666],"iteration":594,"passed_time":281.49922,"remaining_time":191.6087128},
{"learn":[0.5701447122],"iteration":595,"passed_time":281.9602821,"remaining_time":191.1274395},
{"learn":[0.5695431683],"iteration":596,"passed_time":282.414172,"remaining_time":190.6413925},
{"learn":[0.568827454],"iteration":597,"passed_time":282.9238637,"remaining_time":190.1929652},
{"learn":[0.5683518321],"iteration":598,"passed_time":283.3902983,"remaining_time":189.715375},
{"learn":[0.5679758881],"iteration":599,"passed_time":283.8623508,"remaining_time":189.2415672},
{"learn":[0.5676839158],"iteration":600,"passed_time":284.3194231,"remaining_time":188.75782},
{"learn":[0.5672392453],"iteration":601,"passed_time":284.7562666,"remaining_time":188.2607875},
{"learn":[0.5668685746],"iteration":602,"passed_time":285.2140941,"remaining_time":187.7777701},
{"learn":[0.5666481465],"iteration":603,"passed_time":285.6965182,"remaining_time":187.3109623},
{"learn":[0.5665439373],"iteration":604,"passed_time":286.1691629,"remaining_time":186.837718},
{"learn":[0.5661367462],"iteration":605,"passed_time":286.6849268,"remaining_time":186.3925102},
{"learn":[0.5654308595],"iteration":606,"passed_time":287.1501428,"remaining_time":185.9143429},
{"learn":[0.5652340357],"iteration":607,"passed_time":287.592464,"remaining_time":185.421457},
{"learn":[0.5649915809],"iteration":608,"passed_time":288.0126829,"remaining_time":184.9145468},
{"learn":[0.5647005241],"iteration":609,"passed_time":288.475354,"remaining_time":184.4350624},
{"learn":[0.5645626833],"iteration":610,"passed_time":288.9868123,"remaining_time":183.9866939},
{"learn":[0.5645289594],"iteration":611,"passed_time":289.4881187,"remaining_time":183.5316831},
{"learn":[0.5642615297],"iteration":612,"passed_time":289.9731807,"remaining_time":183.0662658},
{"learn":[0.5639376309],"iteration":613,"passed_time":290.408952,"remaining_time":182.5697972},
{"learn":[0.5636897135],"iteration":614,"passed_time":290.9161388,"remaining_time":182.1182332},
{"learn":[0.5632703477],"iteration":615,"passed_time":291.3802659,"remaining_time":181.6396462},
{"learn":[0.5631718178],"iteration":616,"passed_time":291.8505667,"remaining_time":181.1649385},
{"learn":[0.5626578388],"iteration":617,"passed_time":292.3725761,"remaining_time":180.7222072},
{"learn":[0.5618526234],"iteration":618,"passed_time":292.8356671,"remaining_time":180.242955},
{"learn":[0.5614879914],"iteration":619,"passed_time":293.3446885,"remaining_time":179.7919058},
{"learn":[0.5612264135],"iteration":620,"passed_time":293.86539,"remaining_time":179.3477984},
{"learn":[0.5607969067],"iteration":621,"passed_time":294.317964,"remaining_time":178.8620425},
{"learn":[0.5596277625],"iteration":622,"passed_time":294.8309009,"remaining_time":178.4129208},
{"learn":[0.5593517547],"iteration":623,"passed_time":295.2985278,"remaining_time":177.9362924},
{"learn":[0.55907864],"iteration":624,"passed_time":295.7387592,"remaining_time":177.4432555},
{"learn":[0.5588587401],"iteration":625,"passed_time":296.194508,"remaining_time":176.9596581},
{"learn":[0.5584734464],"iteration":626,"passed_time":296.6408025,"remaining_time":176.4705253},
{"learn":[0.558214021],"iteration":627,"passed_time":297.1009664,"remaining_time":175.9897444},
{"learn":[0.5580208741],"iteration":628,"passed_time":297.558337,"remaining_time":175.5073816},
{"learn":[0.5578039204],"iteration":629,"passed_time":298.0191707,"remaining_time":175.027132},
{"learn":[0.55729763],"iteration":630,"passed_time":298.4945651,"remaining_time":174.5554588},
{"learn":[0.5567588876],"iteration":631,"passed_time":298.9746178,"remaining_time":174.0864863},
{"learn":[0.5566992763],"iteration":632,"passed_time":299.4931366,"remaining_time":173.6397806},
{"learn":[0.5563993342],"iteration":633,"passed_time":299.9486887,"remaining_time":173.1564985},
{"learn":[0.5562006961],"iteration":634,"passed_time":300.3724081,"remaining_time":172.6550062},
{"learn":[0.5557842234],"iteration":635,"passed_time":300.7966441,"remaining_time":172.1540542},
{"learn":[0.5556457358],"iteration":636,"passed_time":301.2623252,"remaining_time":171.6769608},
{"learn":[0.5554164573],"iteration":637,"passed_time":301.7798984,"remaining_time":171.2293467},
{"learn":[0.5549312082],"iteration":638,"passed_time":302.2653074,"remaining_time":170.7633427},
{"learn":[0.5547080041],"iteration":639,"passed_time":302.7710243,"remaining_time":170.3087012},
{"learn":[0.5544537417],"iteration":640,"passed_time":303.2813711,"remaining_time":169.8564934},
{"learn":[0.5541739402],"iteration":641,"passed_time":303.7675585,"remaining_time":169.3906323},
{"learn":[0.5538212549],"iteration":642,"passed_time":304.2299214,"remaining_time":168.9114805},
{"learn":[0.5533968792],"iteration":643,"passed_time":304.7366954,"remaining_time":168.456931},
{"learn":[0.55309179],"iteration":644,"passed_time":305.193543,"remaining_time":167.9747407},
{"learn":[0.5528242029],"iteration":645,"passed_time":305.6839667,"remaining_time":167.5110282},
{"learn":[0.5524586602],"iteration":646,"passed_time":306.1821275,"remaining_time":167.0514544},
{"learn":[0.5521087772],"iteration":647,"passed_time":306.6556999,"remaining_time":166.5784049},
{"learn":[0.5517753402],"iteration":648,"passed_time":307.1226747,"remaining_time":166.1017855},
{"learn":[0.5514580367],"iteration":649,"passed_time":307.6086996,"remaining_time":165.6354536},
{"learn":[0.5509613192],"iteration":650,"passed_time":308.1117431,"remaining_time":165.1781849},
{"learn":[0.5505515435],"iteration":651,"passed_time":308.5213428,"remaining_time":164.6709008},
{"learn":[0.5504094105],"iteration":652,"passed_time":309.0452098,"remaining_time":164.2246367},
{"learn":[0.5503051431],"iteration":653,"passed_time":309.5093625,"remaining_time":163.7465434},
{"learn":[0.5497560594],"iteration":654,"passed_time":310.003049,"remaining_time":163.2840487},
{"learn":[0.5497028571],"iteration":655,"passed_time":310.5072613,"remaining_time":162.8269785},
{"learn":[0.5495091068],"iteration":656,"passed_time":310.994828,"remaining_time":162.3610746},
{"learn":[0.5489896753],"iteration":657,"passed_time":311.4235787,"remaining_time":161.8645348},
{"learn":[0.5487893533],"iteration":658,"passed_time":311.9138097,"remaining_time":161.4000138},
{"learn":[0.5482054248],"iteration":659,"passed_time":312.3349767,"remaining_time":160.8998365},
{"learn":[0.5477574005],"iteration":660,"passed_time":312.782391,"remaining_time":160.4133594},
{"learn":[0.5474466725],"iteration":661,"passed_time":313.2948726,"remaining_time":159.960222},
{"learn":[0.5470083112],"iteration":662,"passed_time":313.7958534,"remaining_time":159.5010597},
{"learn":[0.5462814389],"iteration":663,"passed_time":314.2429278,"remaining_time":159.0144936},
{"learn":[0.5460428198],"iteration":664,"passed_time":314.7459142,"remaining_time":158.5562124},
{"learn":[0.5459054618],"iteration":665,"passed_time":315.2514595,"remaining_time":158.0990803},
{"learn":[0.5457907371],"iteration":666,"passed_time":315.7511827,"remaining_time":157.6388963},
{"learn":[0.5456791357],"iteration":667,"passed_time":316.2118207,"remaining_time":157.1591684},
{"learn":[0.5455634117],"iteration":668,"passed_time":316.7363232,"remaining_time":156.7110956},
{"learn":[0.5449729774],"iteration":669,"passed_time":317.2546781,"remaining_time":156.2597668},
{"learn":[0.5447301404],"iteration":670,"passed_time":317.7452034,"remaining_time":155.794593},
{"learn":[0.544058751],"iteration":671,"passed_time":318.2704916,"remaining_time":155.3463114},
{"learn":[0.5437192215],"iteration":672,"passed_time":318.7290697,"remaining_time":154.8653875},
{"learn":[0.5436983242],"iteration":673,"passed_time":319.2512751,"remaining_time":154.4153052},
{"learn":[0.5435675753],"iteration":674,"passed_time":319.7618696,"remaining_time":153.9594187},
{"learn":[0.5435063026],"iteration":675,"passed_time":320.2377617,"remaining_time":153.4867379},
{"learn":[0.5430698762],"iteration":676,"passed_time":320.7210864,"remaining_time":153.0175936},
{"learn":[0.5430008657],"iteration":677,"passed_time":321.2115846,"remaining_time":152.5518145},
{"learn":[0.5427013423],"iteration":678,"passed_time":321.7211431,"remaining_time":152.0949734},
{"learn":[0.5424247596],"iteration":679,"passed_time":322.1970211,"remaining_time":151.6221276},
{"learn":[0.542203826],"iteration":680,"passed_time":322.6986466,"remaining_time":151.1613337},
{"learn":[0.541398165],"iteration":681,"passed_time":323.1967101,"remaining_time":150.6987593},
{"learn":[0.5406615851],"iteration":682,"passed_time":323.6310779,"remaining_time":150.2065178},
{"learn":[0.540239906],"iteration":683,"passed_time":324.0883337,"remaining_time":149.7250197},
{"learn":[0.5400681163],"iteration":684,"passed_time":324.5680318,"remaining_time":149.2539124},
{"learn":[0.5397334515],"iteration":685,"passed_time":325.0029122,"remaining_time":148.7622659},
{"learn":[0.5394965183],"iteration":686,"passed_time":325.4941244,"remaining_time":148.2964497},
{"learn":[0.5386339169],"iteration":687,"passed_time":326.0099185,"remaining_time":147.8417072},
{"learn":[0.5383764459],"iteration":688,"passed_time":326.5216173,"remaining_time":147.384939},
{"learn":[0.5381591671],"iteration":689,"passed_time":327.0013545,"remaining_time":146.913652},
{"learn":[0.5378401759],"iteration":690,"passed_time":327.4674254,"remaining_time":146.4362293},
{"learn":[0.5377240278],"iteration":691,"passed_time":327.9048576,"remaining_time":145.9460927},
{"learn":[0.5365420273],"iteration":692,"passed_time":328.3256291,"remaining_time":145.4487275},
{"learn":[0.536259595],"iteration":693,"passed_time":328.7903706,"remaining_time":144.9709703},
{"learn":[0.5360492753],"iteration":694,"passed_time":329.2891101,"remaining_time":144.5081706},
{"learn":[0.5355393361],"iteration":695,"passed_time":329.7939991,"remaining_time":144.0479536},
{"learn":[0.5353573154],"iteration":696,"passed_time":330.2460698,"remaining_time":143.5646473},
{"learn":[0.5351069769],"iteration":697,"passed_time":330.7021152,"remaining_time":143.0831501},
{"learn":[0.5350343334],"iteration":698,"passed_time":331.1985312,"remaining_time":142.61911},
{"learn":[0.534796566],"iteration":699,"passed_time":331.6589738,"remaining_time":142.1395602},
{"learn":[0.5331860574],"iteration":700,"passed_time":332.1393665,"remaining_time":141.6685743},
{"learn":[0.532912079],"iteration":701,"passed_time":332.6242486,"remaining_time":141.1994674},
{"learn":[0.5325348941],"iteration":702,"passed_time":333.1547754,"remaining_time":140.7495993},
{"learn":[0.5324472685],"iteration":703,"passed_time":333.6673178,"remaining_time":140.2919404},
{"learn":[0.5321424831],"iteration":704,"passed_time":334.1090758,"remaining_time":139.8045069},
{"learn":[0.5321258808],"iteration":705,"passed_time":334.6084576,"remaining_time":139.3411991},
{"learn":[0.5318209624],"iteration":706,"passed_time":335.0573361,"remaining_time":138.8568592},
{"learn":[0.5314023445],"iteration":707,"passed_time":335.560029,"remaining_time":138.3948142},
{"learn":[0.5312093811],"iteration":708,"passed_time":336.0449967,"remaining_time":137.9253795},
{"learn":[0.5310038733],"iteration":709,"passed_time":336.5309551,"remaining_time":137.4563056},
{"learn":[0.5302738396],"iteration":710,"passed_time":337.0109068,"remaining_time":136.9847427},
{"learn":[0.5301103475],"iteration":711,"passed_time":337.4982351,"remaining_time":136.51614},
{"learn":[0.5298714692],"iteration":712,"passed_time":337.9711973,"remaining_time":136.0417021},
{"learn":[0.5297729307],"iteration":713,"passed_time":338.3920174,"remaining_time":135.5463823},
{"learn":[0.5296760006],"iteration":714,"passed_time":338.8903607,"remaining_time":135.0821718},
{"learn":[0.5295201714],"iteration":715,"passed_time":339.3980141,"remaining_time":134.6215587},
{"learn":[0.5293664004],"iteration":716,"passed_time":339.9241936,"remaining_time":134.1681266},
{"learn":[0.5291879667],"iteration":717,"passed_time":340.4651157,"remaining_time":133.7202822},
{"learn":[0.5289956943],"iteration":718,"passed_time":340.9302189,"remaining_time":133.2425473},
{"learn":[0.5288270509],"iteration":719,"passed_time":341.4382113,"remaining_time":132.7815266},
{"learn":[0.528609651],"iteration":720,"passed_time":341.9324631,"remaining_time":132.3150585},
{"learn":[0.5284393197],"iteration":721,"passed_time":342.4118839,"remaining_time":131.8428029},
{"learn":[0.5282785331],"iteration":722,"passed_time":342.8993089,"remaining_time":131.3735942},
{"learn":[0.5281132486],"iteration":723,"passed_time":343.4387343,"remaining_time":130.9241584},
{"learn":[0.5276887508],"iteration":724,"passed_time":343.9039747,"remaining_time":130.4463352},
{"learn":[0.5276252611],"iteration":725,"passed_time":344.4192465,"remaining_time":129.9874291},
{"learn":[0.5270990288],"iteration":726,"passed_time":344.9131145,"remaining_time":129.5203305},
{"learn":[0.5268471143],"iteration":727,"passed_time":345.366617,"remaining_time":129.0380767},
{"learn":[0.5266685299],"iteration":728,"passed_time":345.8242919,"remaining_time":128.5574528},
{"learn":[0.526321404],"iteration":729,"passed_time":346.2606593,"remaining_time":128.069011},
{"learn":[0.5261590647],"iteration":730,"passed_time":346.7691821,"remaining_time":127.607264},
{"learn":[0.5258950725],"iteration":731,"passed_time":347.2626491,"remaining_time":127.139877},
{"learn":[0.5251540688],"iteration":732,"passed_time":347.7298307,"remaining_time":126.6628442},
{"learn":[0.5249827699],"iteration":733,"passed_time":348.1573709,"remaining_time":126.1714723},
{"learn":[0.5245022451],"iteration":734,"passed_time":348.6102637,"remaining_time":125.6894148},
{"learn":[0.5240219839],"iteration":735,"passed_time":349.0959886,"remaining_time":125.2192133},
{"learn":[0.5239309632],"iteration":736,"passed_time":349.5928451,"remaining_time":124.752942},
{"learn":[0.5234701824],"iteration":737,"passed_time":350.0565116,"remaining_time":124.2748049},
{"learn":[0.5233202907],"iteration":738,"passed_time":350.5816748,"remaining_time":123.8184264},
{"learn":[0.5222537532],"iteration":739,"passed_time":351.0130361,"remaining_time":123.3289046},
{"learn":[0.5220506008],"iteration":740,"passed_time":351.4789168,"remaining_time":122.8516052},
{"learn":[0.5219376292],"iteration":741,"passed_time":351.928829,"remaining_time":122.3687842},
{"learn":[0.5213196392],"iteration":742,"passed_time":352.4284042,"remaining_time":121.90323},
{"learn":[0.5211810716],"iteration":743,"passed_time":352.927097,"remaining_time":121.4372807},
{"learn":[0.5210608128],"iteration":744,"passed_time":353.4602514,"remaining_time":120.9830391},
{"learn":[0.5208906369],"iteration":745,"passed_time":353.950366,"remaining_time":120.5139316},
{"learn":[0.5202351868],"iteration":746,"passed_time":354.4366759,"remaining_time":120.0434793},
{"learn":[0.5199841887],"iteration":747,"passed_time":354.9200474,"remaining_time":119.5719946},
{"learn":[0.5199177455],"iteration":748,"passed_time":355.3827654,"remaining_time":119.0935569},
{"learn":[0.5195369384],"iteration":749,"passed_time":355.8795923,"remaining_time":118.6265308},
{"learn":[0.519431678],"iteration":750,"passed_time":356.3594854,"remaining_time":118.1538107},
{"learn":[0.5192551207],"iteration":751,"passed_time":356.8641522,"remaining_time":117.6892417},
{"learn":[0.5190388778],"iteration":752,"passed_time":357.3590575,"remaining_time":117.2213641},
{"learn":[0.5188395892],"iteration":753,"passed_time":357.8480517,"remaining_time":116.7514864},
{"learn":[0.5184926823],"iteration":754,"passed_time":358.3045797,"remaining_time":116.2710225},
{"learn":[0.5180641991],"iteration":755,"passed_time":358.7840067,"remaining_time":115.7980128},
{"learn":[0.5178373557],"iteration":756,"passed_time":359.3009832,"remaining_time":115.3370395},
{"learn":[0.5178040309],"iteration":757,"passed_time":359.8565491,"remaining_time":114.8882386},
{"learn":[0.5174809567],"iteration":758,"passed_time":360.3259065,"remaining_time":114.4117832},
{"learn":[0.5169804337],"iteration":759,"passed_time":360.8146992,"remaining_time":113.941484},
{"learn":[0.516768651],"iteration":760,"passed_time":361.2543708,"remaining_time":113.4557091},
{"learn":[0.5167164813],"iteration":761,"passed_time":361.7614728,"remaining_time":112.9911162},
{"learn":[0.5160803496],"iteration":762,"passed_time":362.2357972,"remaining_time":112.5162306},
{"learn":[0.5158967543],"iteration":763,"passed_time":362.7244573,"remaining_time":112.0457748},
{"learn":[0.5155661562],"iteration":764,"passed_time":363.1849338,"remaining_time":111.5666137},
{"learn":[0.5152981219],"iteration":765,"passed_time":363.6689304,"remaining_time":111.0946863},
{"learn":[0.5150716023],"iteration":766,"passed_time":364.1600425,"remaining_time":110.6248891},
{"learn":[0.5150630768],"iteration":767,"passed_time":364.6316084,"remaining_time":110.1491317},
{"learn":[0.5145747176],"iteration":768,"passed_time":365.1687586,"remaining_time":109.6930861},
{"learn":[0.514380049],"iteration":769,"passed_time":365.6582137,"remaining_time":109.2225833},
{"learn":[0.5142030081],"iteration":770,"passed_time":366.1058873,"remaining_time":108.7396215},
{"learn":[0.5139533734],"iteration":771,"passed_time":366.5463787,"remaining_time":108.25463},
{"learn":[0.513802956],"iteration":772,"passed_time":367.0399745,"remaining_time":107.7853483},
{"learn":[0.5135604422],"iteration":773,"passed_time":367.5030759,"remaining_time":107.3070997},
{"learn":[0.5132532606],"iteration":774,"passed_time":367.9915673,"remaining_time":106.8362615},
{"learn":[0.5126562767],"iteration":775,"passed_time":368.4625773,"remaining_time":106.3603316},
{"learn":[0.5125628603],"iteration":776,"passed_time":368.9664174,"remaining_time":105.8938367},
{"learn":[0.5123265221],"iteration":777,"passed_time":369.4478656,"remaining_time":105.4208562},
{"learn":[0.5121217346],"iteration":778,"passed_time":369.8763762,"remaining_time":104.9328359},
{"learn":[0.5118272013],"iteration":779,"passed_time":370.3531074,"remaining_time":104.4585688},
{"learn":[0.5112857988],"iteration":780,"passed_time":370.8256588,"remaining_time":103.9831233},
{"learn":[0.5111306351],"iteration":781,"passed_time":371.309464,"remaining_time":103.5108224},
{"learn":[0.5106981934],"iteration":782,"passed_time":371.79118,"remaining_time":103.0379132},
{"learn":[0.5105553239],"iteration":783,"passed_time":372.2324931,"remaining_time":102.5538501},
{"learn":[0.5104504075],"iteration":784,"passed_time":372.7530781,"remaining_time":102.0916074},
{"learn":[0.5102987727],"iteration":785,"passed_time":373.2621157,"remaining_time":101.6260722},
{"learn":[0.5099858018],"iteration":786,"passed_time":373.7599983,"remaining_time":101.1574074},
{"learn":[0.509740979],"iteration":787,"passed_time":374.2154443,"remaining_time":100.6772515},
{"learn":[0.5096802921],"iteration":788,"passed_time":374.7052988,"remaining_time":100.20636},
{"learn":[0.5093900948],"iteration":789,"passed_time":375.1841087,"remaining_time":99.73248459},
{"learn":[0.5091642158],"iteration":790,"passed_time":375.6950057,"remaining_time":99.26707482},
{"learn":[0.5089080466],"iteration":791,"passed_time":376.1787998,"remaining_time":98.79443227},
{"learn":[0.5087007381],"iteration":792,"passed_time":376.6673599,"remaining_time":98.32300568},
{"learn":[0.5085007033],"iteration":793,"passed_time":377.1684568,"remaining_time":97.85478854},
{"learn":[0.5082888567],"iteration":794,"passed_time":377.6553106,"remaining_time":97.38281594},
{"learn":[0.5080645639],"iteration":795,"passed_time":378.1411495,"remaining_time":96.91054586},
{"learn":[0.5077822082],"iteration":796,"passed_time":378.5867266,"remaining_time":96.42798682},
{"learn":[0.5067321922],"iteration":797,"passed_time":379.0488023,"remaining_time":95.94969682},
{"learn":[0.5065979763],"iteration":798,"passed_time":379.521029,"remaining_time":95.47400104},
{"learn":[0.5064431862],"iteration":799,"passed_time":380.0022858,"remaining_time":95.00057145},
{"learn":[0.5063044427],"iteration":800,"passed_time":380.4801472,"remaining_time":94.52627876},
{"learn":[0.505521603],"iteration":801,"passed_time":380.9988304,"remaining_time":94.06205539},
{"learn":[0.5053439891],"iteration":802,"passed_time":381.4439584,"remaining_time":93.57965106},
{"learn":[0.5047475028],"iteration":803,"passed_time":381.9625221,"remaining_time":93.11524172},
{"learn":[0.5046449251],"iteration":804,"passed_time":382.4534836,"remaining_time":92.64401155},
{"learn":[0.5044937994],"iteration":805,"passed_time":382.9238989,"remaining_time":92.16778708},
{"learn":[0.5044193612],"iteration":806,"passed_time":383.3699441,"remaining_time":91.68574871},
{"learn":[0.5041944824],"iteration":807,"passed_time":383.8354141,"remaining_time":91.20841523},
{"learn":[0.5037553847],"iteration":808,"passed_time":384.3123044,"remaining_time":90.73380735},
{"learn":[0.5036937194],"iteration":809,"passed_time":384.7754443,"remaining_time":90.25596842},
{"learn":[0.5032288202],"iteration":810,"passed_time":385.2541832,"remaining_time":89.78180102},
{"learn":[0.5029029176],"iteration":811,"passed_time":385.7404259,"remaining_time":89.3093597},
{"learn":[0.5024016833],"iteration":812,"passed_time":386.2197792,"remaining_time":88.83529977},
{"learn":[0.5023068526],"iteration":813,"passed_time":386.7055796,"remaining_time":88.36270001},
{"learn":[0.5022664699],"iteration":814,"passed_time":387.2246643,"remaining_time":87.89762319},
{"learn":[0.5020744933],"iteration":815,"passed_time":387.6890963,"remaining_time":87.42009033},
{"learn":[0.5018955325],"iteration":816,"passed_time":388.1801939,"remaining_time":86.94856241},
{"learn":[0.5017459433],"iteration":817,"passed_time":388.6612852,"remaining_time":86.47476027},
{"learn":[0.5014581502],"iteration":818,"passed_time":389.1140678,"remaining_time":85.9946841},
{"learn":[0.5013834701],"iteration":819,"passed_time":389.6458618,"remaining_time":85.53201845},
{"learn":[0.5012690394],"iteration":820,"passed_time":390.1170734,"remaining_time":85.05597581},
{"learn":[0.5010924218],"iteration":821,"passed_time":390.5977617,"remaining_time":84.58199707},
{"learn":[0.5009399192],"iteration":822,"passed_time":391.0705053,"remaining_time":84.10629337},
{"learn":[0.5008146538],"iteration":823,"passed_time":391.551954,"remaining_time":83.6324562},
{"learn":[0.5006086408],"iteration":824,"passed_time":392.0449847,"remaining_time":83.16105737},
{"learn":[0.500483453],"iteration":825,"passed_time":392.5650153,"remaining_time":82.69529378},
{"learn":[0.4999597537],"iteration":826,"passed_time":393.0788642,"remaining_time":82.22810582},
{"learn":[0.499726865],"iteration":827,"passed_time":393.587899,"remaining_time":81.75980511},
{"learn":[0.4994923814],"iteration":828,"passed_time":394.0468016,"remaining_time":81.28106523},
{"learn":[0.4992563105],"iteration":829,"passed_time":394.5547045,"remaining_time":80.81240936},
{"learn":[0.4990831668],"iteration":830,"passed_time":395.0650486,"remaining_time":80.34415549},
{"learn":[0.4989172142],"iteration":831,"passed_time":395.5493564,"remaining_time":79.87054312},
{"learn":[0.4987248569],"iteration":832,"passed_time":395.9921048,"remaining_time":79.38857323},
{"learn":[0.4985567386],"iteration":833,"passed_time":396.4159516,"remaining_time":78.90293521},
{"learn":[0.4984270945],"iteration":834,"passed_time":396.8799738,"remaining_time":78.42538404},
{"learn":[0.4977728671],"iteration":835,"passed_time":397.3685999,"remaining_time":77.95269185},
{"learn":[0.4975722879],"iteration":836,"passed_time":397.8654499,"remaining_time":77.48156312},
{"learn":[0.4973979777],"iteration":837,"passed_time":398.2711638,"remaining_time":76.99275482},
{"learn":[0.4970757603],"iteration":838,"passed_time":398.7605226,"remaining_time":76.52019564},
{"learn":[0.4968344926],"iteration":839,"passed_time":399.2471008,"remaining_time":76.04706683},
{"learn":[0.4963451406],"iteration":840,"passed_time":399.7621034,"remaining_time":75.57927995},
{"learn":[0.4959801829],"iteration":841,"passed_time":400.2081826,"remaining_time":75.09844756},
{"learn":[0.495939881],"iteration":842,"passed_time":400.7156928,"remaining_time":74.62913852},
{"learn":[0.4953854202],"iteration":843,"passed_time":401.1603461,"remaining_time":74.14812084},
{"learn":[0.4950746642],"iteration":844,"passed_time":401.6092023,"remaining_time":73.66796018},
{"learn":[0.4950274916],"iteration":845,"passed_time":402.0771915,"remaining_time":73.19135636},
{"learn":[0.4948737112],"iteration":846,"passed_time":402.5449519,"remaining_time":72.71473157},
{"learn":[0.4943456991],"iteration":847,"passed_time":403.0024389,"remaining_time":72.23628621},
{"learn":[0.4940488086],"iteration":848,"passed_time":403.4513625,"remaining_time":71.75636718},
{"learn":[0.4935461586],"iteration":849,"passed_time":403.9175822,"remaining_time":71.27957332},
{"learn":[0.4930904191],"iteration":850,"passed_time":404.3932319,"remaining_time":70.8044554},
{"learn":[0.4929789702],"iteration":851,"passed_time":404.8690987,"remaining_time":70.32937395},
{"learn":[0.4929223456],"iteration":852,"passed_time":405.3820475,"remaining_time":69.8606811},
{"learn":[0.4928678269],"iteration":853,"passed_time":405.8787207,"remaining_time":69.38910214},
{"learn":[0.4926532095],"iteration":854,"passed_time":406.37919,"remaining_time":68.91810824},
{"learn":[0.4924104084],"iteration":855,"passed_time":406.8631093,"remaining_time":68.44426138},
{"learn":[0.4922695686],"iteration":856,"passed_time":407.3486561,"remaining_time":67.97066257},
{"learn":[0.4918409053],"iteration":857,"passed_time":407.8768584,"remaining_time":67.50409544},
{"learn":[0.4917059392],"iteration":858,"passed_time":408.37428,"remaining_time":67.03233233},
{"learn":[0.4915722477],"iteration":859,"passed_time":408.8753667,"remaining_time":66.56110621},
{"learn":[0.4914237975],"iteration":860,"passed_time":409.3533991,"remaining_time":66.08608883},
{"learn":[0.4912434023],"iteration":861,"passed_time":409.804901,"remaining_time":65.60681709},
{"learn":[0.4901315079],"iteration":862,"passed_time":410.2552942,"remaining_time":65.12743372},
{"learn":[0.4898297455],"iteration":863,"passed_time":410.7787761,"remaining_time":64.65962216},
{"learn":[0.4896652968],"iteration":864,"passed_time":411.2706417,"remaining_time":64.18674755},
{"learn":[0.4893974993],"iteration":865,"passed_time":411.766803,"remaining_time":63.71449377},
{"learn":[0.4889892146],"iteration":866,"passed_time":412.2225861,"remaining_time":63.23599072},
{"learn":[0.4887330854],"iteration":867,"passed_time":412.6956332,"remaining_time":62.76016542},
{"learn":[0.4884119887],"iteration":868,"passed_time":413.135908,"remaining_time":62.27940615},
{"learn":[0.4883461468],"iteration":869,"passed_time":413.5296451,"remaining_time":61.79178604},
{"learn":[0.4882669058],"iteration":870,"passed_time":413.9665139,"remaining_time":61.31076956},
{"learn":[0.4875861179],"iteration":871,"passed_time":414.4246845,"remaining_time":60.83298121},
{"learn":[0.4872377708],"iteration":872,"passed_time":414.8824263,"remaining_time":60.35517541},
{"learn":[0.4869323964],"iteration":873,"passed_time":415.3994739,"remaining_time":59.88596534},
{"learn":[0.4866532543],"iteration":874,"passed_time":415.8362794,"remaining_time":59.40518277},
{"learn":[0.4865024518],"iteration":875,"passed_time":416.2849002,"remaining_time":58.92617308},
{"learn":[0.4863535305],"iteration":876,"passed_time":416.7629456,"remaining_time":58.45135953},
{"learn":[0.4863194782],"iteration":877,"passed_time":417.2564678,"remaining_time":57.97868915},
{"learn":[0.4859804792],"iteration":878,"passed_time":417.7627346,"remaining_time":57.50772569},
{"learn":[0.4858196912],"iteration":879,"passed_time":418.2380868,"remaining_time":57.03246638},
{"learn":[0.485513716],"iteration":880,"passed_time":418.7318582,"remaining_time":56.55969481},
{"learn":[0.4854984078],"iteration":881,"passed_time":419.2351052,"remaining_time":56.08814332},
{"learn":[0.4853957101],"iteration":882,"passed_time":419.7351211,"remaining_time":55.61609192},
{"learn":[0.4843482604],"iteration":883,"passed_time":420.1911013,"remaining_time":55.13819881},
{"learn":[0.4841895396],"iteration":884,"passed_time":420.6315165,"remaining_time":54.65833266},
{"learn":[0.4840475461],"iteration":885,"passed_time":421.1115817,"remaining_time":54.18365724},
{"learn":[0.4839446503],"iteration":886,"passed_time":421.5723878,"remaining_time":53.70651615},
{"learn":[0.4838420665],"iteration":887,"passed_time":422.0196007,"remaining_time":53.22769739},
{"learn":[0.4835508914],"iteration":888,"passed_time":422.4445149,"remaining_time":52.74616553},
{"learn":[0.4833323594],"iteration":889,"passed_time":422.8884207,"remaining_time":52.26710817},
{"learn":[0.4819101582],"iteration":890,"passed_time":423.3949544,"remaining_time":51.79579127},
{"learn":[0.4817945819],"iteration":891,"passed_time":423.8814066,"remaining_time":51.32196403},
{"learn":[0.4817392688],"iteration":892,"passed_time":424.3460853,"remaining_time":50.84549958},
{"learn":[0.4814008146],"iteration":893,"passed_time":424.8164593,"remaining_time":50.36973679},
{"learn":[0.4811304966],"iteration":894,"passed_time":425.3548998,"remaining_time":49.90197149},
{"learn":[0.4809518432],"iteration":895,"passed_time":425.8397847,"remaining_time":49.42783215},
{"learn":[0.4804695958],"iteration":896,"passed_time":426.3488231,"remaining_time":48.95644234},
{"learn":[0.4803420109],"iteration":897,"passed_time":426.8431079,"remaining_time":48.48329288},
{"learn":[0.4801432928],"iteration":898,"passed_time":427.3635423,"remaining_time":48.01303423},
{"learn":[0.4801007906],"iteration":899,"passed_time":427.8676138,"remaining_time":47.54084597},
{"learn":[0.4797906943],"iteration":900,"passed_time":428.3491899,"remaining_time":47.06611521},
{"learn":[0.4797438642],"iteration":901,"passed_time":428.834095,"remaining_time":46.59173094},
{"learn":[0.4795319799],"iteration":902,"passed_time":429.3491509,"remaining_time":46.12056217},
{"learn":[0.4787660875],"iteration":903,"passed_time":429.7873448,"remaining_time":45.64113396},
{"learn":[0.4787106355],"iteration":904,"passed_time":430.2595031,"remaining_time":45.16536221},
{"learn":[0.478480185],"iteration":905,"passed_time":430.748353,"remaining_time":44.69133022},
{"learn":[0.4782947996],"iteration":906,"passed_time":431.2447208,"remaining_time":44.21803642},
{"learn":[0.477672553],"iteration":907,"passed_time":431.7373818,"remaining_time":43.74431622},
{"learn":[0.4775510548],"iteration":908,"passed_time":432.2218477,"remaining_time":43.26973392},
{"learn":[0.4772332078],"iteration":909,"passed_time":432.7297521,"remaining_time":42.79744801},
{"learn":[0.4763727757],"iteration":910,"passed_time":433.2245911,"remaining_time":42.32380747},
{"learn":[0.4762306152],"iteration":911,"passed_time":433.7161924,"remaining_time":41.84980804},
{"learn":[0.4760237143],"iteration":912,"passed_time":434.2357284,"remaining_time":41.37843195},
{"learn":[0.4758431793],"iteration":913,"passed_time":434.7616649,"remaining_time":40.90755271},
{"learn":[0.4756621222],"iteration":914,"passed_time":435.2789383,"remaining_time":40.43574836},
{"learn":[0.4754551258],"iteration":915,"passed_time":435.761397,"remaining_time":39.96065213},
{"learn":[0.475274825],"iteration":916,"passed_time":436.2255215,"remaining_time":39.48388036},
{"learn":[0.4750766948],"iteration":917,"passed_time":436.707573,"remaining_time":39.00873745},
{"learn":[0.4749348422],"iteration":918,"passed_time":437.2089384,"remaining_time":38.53528184},
{"learn":[0.4745536742],"iteration":919,"passed_time":437.7107475,"remaining_time":38.06180413},
{"learn":[0.4744347306],"iteration":920,"passed_time":438.1802149,"remaining_time":37.58549075},
{"learn":[0.474168462],"iteration":921,"passed_time":438.6302155,"remaining_time":37.10754535},
{"learn":[0.4740667994],"iteration":922,"passed_time":439.0715999,"remaining_time":36.62894171},
{"learn":[0.4739442376],"iteration":923,"passed_time":439.5861355,"remaining_time":36.15643538},
{"learn":[0.47376125],"iteration":924,"passed_time":440.0610918,"remaining_time":35.68062907},
{"learn":[0.4736210184],"iteration":925,"passed_time":440.5533642,"remaining_time":35.20620837},
{"learn":[0.473542027],"iteration":926,"passed_time":441.0429526,"remaining_time":34.7315378},
{"learn":[0.4733541007],"iteration":927,"passed_time":441.4841957,"remaining_time":34.25308415},
{"learn":[0.4730246344],"iteration":928,"passed_time":441.9913032,"remaining_time":33.77974438},
{"learn":[0.4729381786],"iteration":929,"passed_time":442.4305987,"remaining_time":33.30122786},
{"learn":[0.4726990295],"iteration":930,"passed_time":442.9473892,"remaining_time":32.82853905},
{"learn":[0.4723913976],"iteration":931,"passed_time":443.4257614,"remaining_time":32.35295255},
{"learn":[0.4721468661],"iteration":932,"passed_time":443.9348757,"remaining_time":31.87956771},
{"learn":[0.4720028639],"iteration":933,"passed_time":444.3937698,"remaining_time":31.40255761},
{"learn":[0.4718604995],"iteration":934,"passed_time":444.863996,"remaining_time":30.92637406},
{"learn":[0.4716870783],"iteration":935,"passed_time":445.3384802,"remaining_time":30.45049437},
{"learn":[0.4715804405],"iteration":936,"passed_time":445.7891685,"remaining_time":29.97301773},
{"learn":[0.4713758574],"iteration":937,"passed_time":446.2437989,"remaining_time":29.49585878},
{"learn":[0.4710931547],"iteration":938,"passed_time":446.6478508,"remaining_time":29.01546208},
{"learn":[0.4709484549],"iteration":939,"passed_time":447.1277902,"remaining_time":28.54007172},
{"learn":[0.4707018378],"iteration":940,"passed_time":447.6135344,"remaining_time":28.06503563},
{"learn":[0.4705216951],"iteration":941,"passed_time":448.0716192,"remaining_time":27.58827379},
{"learn":[0.4703899308],"iteration":942,"passed_time":448.5341043,"remaining_time":27.11181754},
{"learn":[0.4701955865],"iteration":943,"passed_time":448.9789396,"remaining_time":26.63434387},
{"learn":[0.469996869],"iteration":944,"passed_time":449.450745,"remaining_time":26.15850897},
{"learn":[0.4696947368],"iteration":945,"passed_time":449.8763253,"remaining_time":25.68004394},
{"learn":[0.4694631726],"iteration":946,"passed_time":450.3230453,"remaining_time":25.20287371},
{"learn":[0.46937974],"iteration":947,"passed_time":450.7859706,"remaining_time":24.72665662},
{"learn":[0.4692979478],"iteration":948,"passed_time":451.2636249,"remaining_time":24.25125908},
{"learn":[0.4690433413],"iteration":949,"passed_time":451.7293851,"remaining_time":23.77523079},
{"learn":[0.4688723722],"iteration":950,"passed_time":452.1600434,"remaining_time":23.29741548},
{"learn":[0.4686747196],"iteration":951,"passed_time":452.617075,"remaining_time":22.82102899},
{"learn":[0.4684232222],"iteration":952,"passed_time":453.0835431,"remaining_time":22.3451485},
{"learn":[0.4682515241],"iteration":953,"passed_time":453.5497393,"remaining_time":21.86927464},
{"learn":[0.4682316383],"iteration":954,"passed_time":454.0863676,"remaining_time":21.39673983},
{"learn":[0.4680472393],"iteration":955,"passed_time":454.5300107,"remaining_time":20.91979129},
{"learn":[0.4678335575],"iteration":956,"passed_time":455.0017081,"remaining_time":20.44417288},
{"learn":[0.4676536038],"iteration":957,"passed_time":455.4836868,"remaining_time":19.96901341},
{"learn":[0.4671984294],"iteration":958,"passed_time":455.9648734,"remaining_time":19.49380585},
{"learn":[0.4671040618],"iteration":959,"passed_time":456.4059706,"remaining_time":19.01691544},
{"learn":[0.4668914097],"iteration":960,"passed_time":456.8946316,"remaining_time":18.54202979},
{"learn":[0.4667410084],"iteration":961,"passed_time":457.3708953,"remaining_time":18.0666258},
{"learn":[0.4666437644],"iteration":962,"passed_time":457.9021074,"remaining_time":17.59333123},
{"learn":[0.4666117713],"iteration":963,"passed_time":458.39115,"remaining_time":17.1183417},
{"learn":[0.4665187412],"iteration":964,"passed_time":458.8922904,"remaining_time":16.64376183},
{"learn":[0.4661178649],"iteration":965,"passed_time":459.3369203,"remaining_time":16.16713798},
{"learn":[0.4660554399],"iteration":966,"passed_time":459.8043147,"remaining_time":15.69135717},
{"learn":[0.4659776802],"iteration":967,"passed_time":460.247157,"remaining_time":15.21478205},
{"learn":[0.4658364345],"iteration":968,"passed_time":460.7285622,"remaining_time":14.73951025},
{"learn":[0.4656848939],"iteration":969,"passed_time":461.1756636,"remaining_time":14.26316485},
{"learn":[0.4655464609],"iteration":970,"passed_time":461.6307775,"remaining_time":13.787119},
{"learn":[0.4649268181],"iteration":971,"passed_time":462.1022114,"remaining_time":13.31158634},
{"learn":[0.4647879152],"iteration":972,"passed_time":462.5486253,"remaining_time":12.83536781},
{"learn":[0.4646476717],"iteration":973,"passed_time":462.9910702,"remaining_time":12.35910454},
{"learn":[0.4646096993],"iteration":974,"passed_time":463.4123813,"remaining_time":11.88236875},
{"learn":[0.4645216369],"iteration":975,"passed_time":463.8889547,"remaining_time":11.40710544},
{"learn":[0.4644511984],"iteration":976,"passed_time":464.3698227,"remaining_time":10.93194055},
{"learn":[0.4643193613],"iteration":977,"passed_time":464.8590358,"remaining_time":10.45695172},
{"learn":[0.4641374957],"iteration":978,"passed_time":465.3181087,"remaining_time":9.981287317},
{"learn":[0.4639510227],"iteration":979,"passed_time":465.7651353,"remaining_time":9.505410925},
{"learn":[0.4638275103],"iteration":980,"passed_time":466.1659698,"remaining_time":9.028698702},
{"learn":[0.4637005159],"iteration":981,"passed_time":466.6327005,"remaining_time":8.553348888},
{"learn":[0.4633298683],"iteration":982,"passed_time":467.1129774,"remaining_time":8.07825088},
{"learn":[0.4632459787],"iteration":983,"passed_time":467.6031343,"remaining_time":7.603302997},
{"learn":[0.4631559289],"iteration":984,"passed_time":468.072738,"remaining_time":7.128011239},
{"learn":[0.4628976555],"iteration":985,"passed_time":468.4807417,"remaining_time":6.651856373},
{"learn":[0.4627940672],"iteration":986,"passed_time":468.9625239,"remaining_time":6.176811359},
{"learn":[0.4627451339],"iteration":987,"passed_time":469.4557854,"remaining_time":5.70189213},
{"learn":[0.462524234],"iteration":988,"passed_time":469.9415587,"remaining_time":5.226852524},
{"learn":[0.4624698451],"iteration":989,"passed_time":470.4176895,"remaining_time":4.751693833},
{"learn":[0.4623409423],"iteration":990,"passed_time":470.9040913,"remaining_time":4.27662646},
{"learn":[0.4622520104],"iteration":991,"passed_time":471.3956523,"remaining_time":3.801577841},
{"learn":[0.4621599945],"iteration":992,"passed_time":471.8569612,"remaining_time":3.326282708},
{"learn":[0.4618496204],"iteration":993,"passed_time":472.3226563,"remaining_time":2.851042191},
{"learn":[0.4616903241],"iteration":994,"passed_time":472.7919864,"remaining_time":2.375839128},
{"learn":[0.4615955143],"iteration":995,"passed_time":473.2606566,"remaining_time":1.900645207},
{"learn":[0.4612113976],"iteration":996,"passed_time":473.6976977,"remaining_time":1.425369201},
{"learn":[0.4610076907],"iteration":997,"passed_time":474.1503465,"remaining_time":0.9502010953},
{"learn":[0.4609563626],"iteration":998,"passed_time":474.6006002,"remaining_time":0.4750756759},
{"learn":[0.460538844],"iteration":999,"passed_time":475.0741207,"remaining_time":0}
]}